p_layer.v
module p_layer(input [63:0] state,      // origin data
               output wire [63:0] res); // p layer changed data

assign   res = {
state[0],state[4],state[8],state[12],state[16],state[20],state[24],state[28],
state[32],state[36],state[40],state[44],state[48],state[52],state[56],state[60],
state[1],state[5],state[9],state[13],state[17],state[21],state[25],state[29],
state[33],state[37],state[41],state[45],state[49],state[53],state[57],state[61],
state[2],state[6],state[10],state[14],state[18],state[22],state[26],state[30],
state[34],state[38],state[42],state[46],state[50],state[54],state[58],state[62],
state[3],state[7],state[11],state[15],state[19],state[23],state[27],state[31],
state[35],state[39],state[43],state[47],state[51],state[55],state[59],state[63]
};

endmodule

p_round.v
`include "p_layer.v"

module p_round(input [63:0] state,        // current cipher text
               input [79:0] keys,         // current key
               input [4:0] round_counter, // round counter
               output [63:0] res,         // next cipher text
               output [79:0] r_keys);     // next round key


wire   [63:0] tem0;
wire   [63:0] tem1;

reg [3:0] sbox[15:0]; // s box for sBoxLayer

initial begin
    sbox[0]  = 12;  sbox[1]  = 5; sbox[2]  = 6;  sbox[3]  = 11;
    sbox[4]  = 9;   sbox[5]  = 0; sbox[6]  = 10; sbox[7]  = 13;
    sbox[8]  = 3;  sbox[9]  = 14;sbox[10]  = 15; sbox[11]  = 8;
    sbox[12] = 4; sbox[13] = 7;sbox[14] = 1;  sbox[15] = 2;
end

// add round key
assign tem0 = state ^ keys[63:0];

// sBoxLayer
assign tem1 = {
sbox[tem0[3:0]],sbox[tem0[7:4]],sbox[tem0[11:8]],sbox[tem0[15:12]],
sbox[tem0[19:16]],sbox[tem0[23:20]],sbox[tem0[27:24]],sbox[tem0[31:28]],
sbox[tem0[35:32]],sbox[tem0[39:36]],sbox[tem0[43:40]],sbox[tem0[47:44]],
sbox[tem0[51:48]],sbox[tem0[55:52]],sbox[tem0[59:56]],sbox[tem0[63:60]]
};

// KeyExtend
assign     r_keys = {
sbox[keys[64:61]],keys[79:65],keys[40:0],(keys[45:41])^round_counter,keys[60:46]
};

// pLayer
p_layer      u_p_layer(
.state(tem1),
.res(res)
);

endmodule

p.v
`include "p_round.v"

module p(input [0:63] state,    // PlainText
         input [0:79] keys,     // key
         input clk,             // clock
         output [0:63] result);

reg   [0:7] cnt; /*synthesis syn_preserve = 1*/

reg   [0:63]  res;
reg   [0:79]  k;
wire  [0:63]  next_res;
wire  [0:79]  r_keys;

initial  begin
    cnt <= 0;
end

assign  result = res ^k[0:63];

// update the count,res,keys,ready
always @(posedge  clk)  begin
    cnt <= (cnt^31)? cnt+1: 0;
    res <= ((cnt) ?next_res:state) ;
    k   <= ((cnt) ?r_keys:keys) ;
end

p_round   u_p_round(
.res(next_res),
.r_keys(r_keys),
.state(res),
.keys(k),
.round_counter(cnt[3:7]));

endmodule

tb_p.v
`timescale  1ns / 1ps
`include "p.v"
module tb_p();
    parameter PERIOD = 10;
    reg clk;
    reg rst_n;
    reg [63:0] state;
    reg [79:0] keys;
    reg [23:0] counter;
    wire [63:0] result;
    
    // generate colck
    initial begin
        rst_n = 1'b1;
        clk   = 1'b0;
        forever #(PERIOD/2)
            clk = ~clk;
    end
    
    initial begin
        // state = 64'hffff_ffff_ffff_ffff;
        // keys  = 80'hffff_ffff_ffff_ffff_ffff;
        state    = 64'h0000_0000_0000_0000;
        keys     = 80'h0000_0000_0000_0000_0000;
    end
    
    
    p u_p(
    .result(result),
    .state(state),
    .keys(keys),
    .clk(clk));
    
    initial begin
        $dumpfile("./wave.vcd");
        $dumpvars(0, tb_p);
        #(PERIOD*40) $finish;
    end
    
endmodule

wave.vcd
$date
	Fri Feb 24 20:33:11 2023
$end
$version
	Icarus Verilog
$end
$timescale
	1ps
$end
$scope module tb_p $end
$scope module u_p $end
$var wire 1 ! clk $end
$var wire 80 " keys [0:79] $end
$var wire 64 # result [0:63] $end
$var wire 64 $ state [0:63] $end
$var wire 80 % r_keys [0:79] $end
$var wire 64 & next_res [0:63] $end
$var reg 8 ' cnt [0:7] $end
$var reg 80 ( k [0:79] $end
$var reg 64 ) res [0:63] $end
$scope module u_p_round $end
$var wire 80 * keys [0:79] $end
$var wire 5 + round_counter [0:4] $end
$var wire 64 , state [0:63] $end
$var wire 64 - tem0 [0:63] $end
$var wire 64 . tem1 [0:63] $end
$var wire 64 / res [0:63] $end
$var wire 80 0 r_keys [0:79] $end
$scope module u_pLayer $end
$var wire 64 1 state [0:63] $end
$var wire 64 2 res [0:63] $end
$upscope $end
$upscope $end
$upscope $end
$upscope $end
$enddefinitions $end
$comment Show the parameter values. $end
$dumpall
$end
#0
$dumpvars
bx 2
bx 1
bx 0
bx /
bx .
bx -
bx ,
b0 +
bx *
bx )
bx (
b0 '
bx &
bx %
b1111111111111111111111111111111111111111111111111111111111111111 $
bx #
b11111111111111111111111111111111111111111111111111111111111111111111111111111111 "
0!
$end
#5000
b1111111111111111111111111111111100000000000000000000000000000000 &
b1111111111111111111111111111111100000000000000000000000000000000 /
b1111111111111111111111111111111100000000000000000000000000000000 2
b1100110011001100110011001100110011001100110011001100110011001100 .
b1100110011001100110011001100110011001100110011001100110011001100 1
b0 #
b0 -
b101111111111111111111111111111111111111111111111111111111111110111111111111111 %
b101111111111111111111111111111111111111111111111111111111111110111111111111111 0
b1 +
b11111111111111111111111111111111111111111111111111111111111111111111111111111111 (
b11111111111111111111111111111111111111111111111111111111111111111111111111111111 *
b1111111111111111111111111111111111111111111111111111111111111111 )
b1111111111111111111111111111111111111111111111111111111111111111 ,
b1 '
1!
#10000
0!
#15000
b111111100000000111111110000000010000000111111111000000000000000 &
b111111100000000111111110000000010000000111111111000000000000000 /
b111111100000000111111110000000010000000111111111000000000000000 2
b111110011001100110011001100110000100010001000100010001000100010 .
b111110011001100110011001100110000100010001000100010001000100010 1
b11111111111111110010111111111111111111111111111111111111111101111111111111111 %
b11111111111111110010111111111111111111111111111111111111111101111111111111111 0
b1101000000000000000000000000000011111111111111111111111111111111 -
b1101000000000000000000000000000011111111111111111111111111111111 #
b10 +
b101111111111111111111111111111111111111111111111111111111111110111111111111111 (
b101111111111111111111111111111111111111111111111111111111111110111111111111111 *
b1111111111111111111111111111111100000000000000000000000000000000 )
b1111111111111111111111111111111100000000000000000000000000000000 ,
b10 '
1!
#20000
0!
#25000
b1100010010111000010011001011100010110111010001100000110010001001 &
b1100010010111000010011001011100010110111010001100000110010001001 /
b1100010010111000010011001011100010110111010001100000110010001001 2
b1010110000100010010111110010001011010010110011001101001000100001 .
b1010110000100010010111110010001011010010110011001101001000100001 1
b1111111111111111110001111111111111111001011111111111111111111100111111111111111 %
b1111111111111111110001111111111111111001011111111111111111111100111111111111111 0
b110000011111111000110101111111101111111000000000111111111111110 -
b110000011111111000110101111111101111111000000000111111111111110 #
b11 +
b11111111111111110010111111111111111111111111111111111111111101111111111111111 (
b11111111111111110010111111111111111111111111111111111111111101111111111111111 *
b111111100000000111111110000000010000000111111111000000000000000 )
b111111100000000111111110000000010000000111111111000000000000000 ,
b11 '
1!
#30000
0!
#35000
b1111101111010111000110010001001100001100001111000011101110000111 &
b1111101111010111000110010001001100001100001111000011101110000111 /
b1111101111010111000110010001001100001100001111000011101110000111 2
b1000100010011101111100101001110110011000001011100010101111011101 .
b1000100010011101111100101001110110011000001011100010101111011101 1
b1001111111111111110111111111111111111000111111111111111100101011111111111111111 %
b1001111111111111110111111111111111111000111111111111111100101011111111111111111 0
b1011101101000111101011110100011101001011111110011111001101110111 -
b1011101101000111101011110100011101001011111110011111001101110111 #
b100 +
b1111111111111111110001111111111111111001011111111111111111111100111111111111111 (
b1111111111111111110001111111111111111001011111111111111111111100111111111111111 *
b1100010010111000010011001011100010110111010001100000110010001001 )
b1100010010111000010011001011100010110111010001100000110010001001 ,
b100 '
1!
#40000
0!
#45000
b1100010001110100001000010100101100111100100100010101001000110110 &
b1100010001110100001000010100101100111100100100010101001000110110 /
b1100010001110100001000010100101100111100100100010101001000110110 2
b1000100101100011001010100001010000101100100110110100100101010110 .
b1000100101100011001010100001010000101100100110110100100101010110 1
b10001111111111111110100111111111111111011111111111111111100011010111111111110010 %
b10001111111111111110100111111111111111011111111111111111100011010111111111110010 0
b1011010000101000111101101110110011110000010000111100010000010010 -
b1011010000101000111101101110110011110000010000111100010000010010 #
b101 +
b1001111111111111110111111111111111111000111111111111111100101011111111111111111 (
b1001111111111111110111111111111111111000111111111111111100101011111111111111111 *
b1111101111010111000110010001001100001100001111000011101110000111 )
b1111101111010111000110010001001100001100001111000011101110000111 ,
b101 '
1!
#50000
0!
#55000
b1101001100101011000010001100110000100100001011001010010101011100 &
b1101001100101011000010001100110000100100001011001010010101011100 /
b1101001100101011000010001100110000100100001011001010010101011100 2
b1001100000111000010000111000100101000101101000011111011110001000 .
b1001100000111000010000111000100101000101101000011111011110001000 1
b11111111111111100101000111111111111111010011111111111111101111001111111111110001 %
b11111111111111100101000111111111111111010011111111111111101111001111111111110001 0
b100101110001011110010001011010011000001011011101010110110111011 -
b100101110001011110010001011010011000001011011101010110110111011 #
b110 +
b10001111111111111110100111111111111111011111111111111111100011010111111111110010 (
b10001111111111111110100111111111111111011111111111111111100011010111111111110010 *
b1100010001110100001000010100101100111100100100010101001000110110 )
b1100010001110100001000010100101100111100100100010101001000110110 ,
b110 '
1!
#60000
0!
#65000
b11101010101111001001110010110100111110101000010001110110110 &
b11101010101111001001110010110100111110101000010001110110110 /
b11101010101111001001110010110100111110101000010001110110110 2
b110010001110000000011101011101101111110010110110000111100011100 .
b110010001110000000011101011101101111110010110110000111100011100 1
b11101111111111100011111111111111110010100011111111111111101001000111111111110111 %
b11101111111111100011111111111111110010100011111111111111101001000111111111110111 0
b10110011010101010110010011001111011001000100110101101011100000 -
b10110011010101010110010011001111011001000100110101101011100000 #
b111 +
b11111111111111100101000111111111111111010011111111111111101111001111111111110001 (
b11111111111111100101000111111111111111010011111111111111101111001111111111110001 *
b1101001100101011000010001100110000100100001011001010010101011100 )
b1101001100101011000010001100110000100100001011001010010101011100 ,
b111 '
1!
#70000
0!
#75000
b11010110010000001010110100111101101001110010011110101101101010 &
b11010110010000001010110100111101101001110010011110101101101010 /
b11010110010000001010110100111101101001110010011110101101101010 2
b1001111111000011110000101111110100111000110000111010001010110 .
b1001111111000011110000101111110100111000110000111010001010110 1
b111111111111101111110111111111110001111111111111111001010000111111111111110100 %
b111111111111101111110111111111110001111111111111111001010000111111111111110100 0
b1110100010101011110110110001101001101101111010111101110000010010 -
b1110100010101011110110110001101001101101111010111101110000010010 #
b1000 +
b11101111111111100011111111111111110010100011111111111111101001000111111111110111 (
b11101111111111100011111111111111110010100011111111111111101001000111111111110111 *
b11101010101111001001110010110100111110101000010001110110110 )
b11101010101111001001110010110100111110101000010001110110110 ,
b1000 '
1!
#80000
0!
#85000
b1110011110110001110010011000111101101100101101110101100011101000 &
b1110011110110001110010011000111101101100101101110101100011101000 /
b1110011110110001110010011000111101101100101101110101100011101000 2
b1100111110100001011110101000110011110001101110100101011001101110 .
b1100111110100001011110101000110011110001101110100101011001101110 1
b11011111111111101000011111111111110111111011111111111000111110110111111100101000 %
b11011111111111101000011111111111110111111011111111111000111110110111111100101000 0
b101001101110110101101011000010101110001101100001001000101001 -
b101001101110110101101011000010101110001101100001001000101001 #
b1001 +
b111111111111101111110111111111110001111111111111111001010000111111111111110100 (
b111111111111101111110111111111110001111111111111111001010000111111111111110100 *
b11010110010000001010110100111101101001110010011110101101101010 )
b11010110010000001010110100111101101001110010011110101101101010 ,
b1001 '
1!
#90000
0!
#95000
b1010101111101101000000110010111011010000010110011110111001011011 &
b1010101111101101000000110010111011010000010110011110111001011011 /
b1010101111101101000000110010111011010000010110011110111001011011 2
b1011001110010010100100011101110010001011110000111111110001011011 .
b1011001110010010100100011101110010001011110000111111110001011011 1
b10101111111001010001101111111111110100001111111111111011111100101111111100011111 %
b10101111111001010001101111111111110100001111111111111011111100101111111100011111 0
b11100001001111010011100111000010110011000010001010000000010011 -
b11100001001111010011100111000010110011000010001010000000010011 #
b1010 +
b11011111111111101000011111111111110111111011111111111000111110110111111100101000 (
b11011111111111101000011111111111110111111011111111111000111110110111111100101000 *
b1110011110110001110010011000111101101100101101110101100011101000 )
b1110011110110001110010011000111101101100101101110101100011101000 ,
b1010 '
1!
#100000
0!
#105000
b1110000011110011101010111110101100010110001100110101111100101010 &
b1110000011110011101010111110101100010110001100110101111100101010 /
b1110000011110011101010111110101100010110001100110101111100101010 2
b1100100111000011010100110111010111001100111110100101000011111110 .
b1100100111000011010100110111010111001100111110100101000011111110 1
b1111111000111111010111111100101000110111111111111010000110100111111101111110 %
b1111111000111111010111111100101000110111111111111010000110100111111101111110 0
b10000001000000110001101000100000000101001100001010110101001 -
b10000001000000110001101000100000000101001100001010110101001 #
b1011 +
b10101111111001010001101111111111110100001111111111111011111100101111111100011111 (
b10101111111001010001101111111111110100001111111111111011111100101111111100011111 *
b1010101111101101000000110010111011010000010110011110111001011011 )
b1010101111101101000000110010111011010000010110011110111001011011 ,
b1011 '
1!
#110000
0!
#115000
b1000110101011001100110001100101000000000010101010011100101010 &
b1000110101011001100110001100101000000000010101010011100101010 /
b1000110101011001100110001100101000000000010101010011100101010 2
b1001001011100000000010101110110000000100101001111000010111100 .
b1001001011100000000010101110110000000100101001111000010111100 1
b10011111111011111100000111111100011111101011111110010100011010011111111101000011 %
b10011111111011111100000111111100011111101011111110010100011010011111111101000011 0
b1110111100010000010111100001011110110101010011001010010100110000 -
b1110111100010000010111100001011110110101010011001010010100110000 #
b1100 +
b1111111000111111010111111100101000110111111111111010000110100111111101111110 (
b1111111000111111010111111100101000110111111111111010000110100111111101111110 *
b1110000011110011101010111110101100010110001100110101111100101010 )
b1110000011110011101010111110101100010110001100110101111100101010 ,
b1100 '
1!
#120000
0!
#125000
b11000010101111000001000000000010001100100011011111001011001111 &
b11000010101111000001000000000010001100100011011111001011001111 /
b11000010101111000001000000000010001100100011011111001011001111 2
b11000110011001001001100001000010110001100000001011101110011011 .
b11000110011001001001100001000010110001100000001011101110011011 1
b10111111111010000111001111111101111110000011111110001111110100010111001010001101 %
b10111111111010000111001111111101111110000011111110001111110100010111001010001101 0
b1000111001000100111100101110010100111110101101010011001101000011 -
b1000111001000100111100101110010100111110101101010011001101000011 #
b1101 +
b10011111111011111100000111111100011111101011111110010100011010011111111101000011 (
b10011111111011111100000111111100011111101011111110010100011010011111111101000011 *
b1000110101011001100110001100101000000000010101010011100101010 )
b1000110101011001100110001100101000000000010101010011100101010 ,
b1101 '
1!
#130000
0!
#135000
b11110011101000000111011001111011000011000101001011110111001111 &
b11110011101000000111011001111011000011000101001011110111001111 /
b11110011101000000111011001111011000011000101001011110111001111 2
b11001010011101110111010010011111011001100001101101011101010001 .
b11001010011101110111010010011111011001100001101101011101010001 1
b1101110010100011011011111111101000011100111111110111111000000001111000111111010 %
b1101110010100011011011111111101000011100111111110111111000000001111000111111010 0
b1000111101000111011101111111110101110100101100100111110100011110 -
b1000111101000111011101111111110101110100101100100111110100011110 #
b1110 +
b10111111111010000111001111111101111110000011111110001111110100010111001010001101 (
b10111111111010000111001111111101111110000011111110001111110100010111001010001101 *
b11000010101111000001000000000010001100100011011111001011001111 )
b11000010101111000001000000000010001100100011011111001011001111 ,
b1110 '
1!
#140000
0!
#145000
b11111100111000010111001100111001011111011001010000110101000000 &
b11111100111000010111001100111001011111011001010000110101000000 /
b11111100111000010111001100111001011111011001010000110101000000 2
b11010001110111111111010101101000111101010001100011001000010 .
b11010001110111111111010101101000111101010001100011001000010 1
b1011110001111110100110111001010001101101111111110100001110010000111011111100000 %
b1011110001111110100110111001010001101101111111110100001110010000111011111100000 0
b101001010111001101010100110001111001101011010110000001011001111 -
b101001010111001101010100110001111001101011010110000001011001111 #
b1111 +
b1101110010100011011011111111101000011100111111110111111000000001111000111111010 (
b1101110010100011011011111111101000011100111111110111111000000001111000111111010 *
b11110011101000000111011001111011000011000101001011110111001111 )
b11110011101000000111011001111011000011000101001011110111001111 ,
b1111 '
1!
#150000
0!
#155000
b1011001111111000011111100111110010000000111110110101110100011011 &
b1011001111111000011111100111110010000000111110110101110100011011 /
b1011001111111000011111100111110010000000111110110101110100011011 2
b1010010111001101010101011100100110101110111011111111010000110011 .
b1010010111001101010101011100100110101110111011111111010000110011 1
b11001110111111000000101111000111111010011011100101000110110101111111010000111001 %
b11001110111111000000101111000111111010011011100101000110110101111111010000111001 0
b110000100000111000100010000010001101001100110101010110010001000 -
b110000100000111000100010000010001101001100110101010110010001000 #
b10000 +
b1011110001111110100110111001010001101101111111110100001110010000111011111100000 (
b1011110001111110100110111001010001101101111111110100001110010000111011111100000 *
b11111100111000010111001100111001011111011001010000110101000000 )
b11111100111000010111001100111001011111011001010000110101000000 ,
b10000 '
1!
#160000
0!
#165000
b1011101111100100111010000101101101000000110100001101100000101000 &
b1011101111100100111010000101101101000000110100001101100000101000 /
b1011101111100100111010000101101101000000110100001101100000101000 2
b1101011111001001110100001000100010101110100101100101100001000100 .
b1101011111001001110100001000100010101110100101100101100001000100 1
b101110100001110011100111011111100000010111100011111101001111111010100011011010 %
b101110100001110011100111011111100000010111100011111101001111111010100011011010 0
b111110100000100011101011011101101101001010000100001101111001100 -
b111110100000100011101011011101101101001010000100001101111001100 #
b10001 +
b11001110111111000000101111000111111010011011100101000110110101111111010000111001 (
b11001110111111000000101111000111111010011011100101000110110101111111010000111001 *
b1011001111111000011111100111110010000000111110110101110100011011 )
b1011001111111000011111100111110010000000111110110101110100011011 ,
b10001 '
1!
#170000
0!
#175000
b1011000100100001100011001110101110111010001110000001111101110011 &
b1011000100100001100011001110101110111010001110000001111101110011 /
b1011000100100001100011001110101110111010001110000001111101110011 2
b1110000010101011011101010011100101000101111100110110000001011101 .
b1110000010101011011101010011100101000101111100110110000001011101 1
b100101000110110100010111010000111001110011101111110000001001100001111110100111 %
b100101000110110100010111010000111001110011101111110000001001100001111110100111 0
b1001010101100011110100011000010011000001101010000010010100010111 -
b1001010101100011110100011000010011000001101010000010010100010111 #
b10010 +
b101110100001110011100111011111100000010111100011111101001111111010100011011010 (
b101110100001110011100111011111100000010111100011111101001111111010100011011010 *
b1011101111100100111010000101101101000000110100001101100000101000 )
b1011101111100100111010000101101101000000110100001101100000101000 ,
b10010 '
1!
#180000
0!
#185000
b1111011100110000100111000110000010110110010101000111001001011000 &
b1111011100110000100111000110000010110110010101000111001001011000 /
b1111011100110000100111000110000010110110010101000111001001011000 2
b1110100110111111010011101011100000000111110010110001001000000000 .
b1110100110111111010011101011100000000111110010110001001000000000 1
b1000011111101001110010010100011011010001011101000011100111011101111111000000100 %
b1000011111101001110010010100011011010001011101000011100111011101111111000000100 0
b1001010000111010110010010011101101011101000000111110111101010101 -
b1001010000111010110010010011101101011101000000111110111101010101 #
b10011 +
b100101000110110100010111010000111001110011101111110000001001100001111110100111 (
b100101000110110100010111010000111001110011101111110000001001100001111110100111 *
b1011000100100001100011001110101110111010001110000001111101110011 )
b1011000100100001100011001110101110111010001110000001111101110011 ,
b10011 '
1!
#190000
0!
#195000
b1101100100001011001010101000000000000101100010010101110111110100 &
b1101100100001011001010101000000000000101100010010101110111110100 /
b1101100100001011001010101000000000000101100010010101110111110100 2
b1000100101001001110100110100101101110001000100011010000110001010 .
b1000100101001001110100110100101101110001000100011010000110001010 1
b1111111110000001000100001111110100111001001010001101101000111010100001110011101 %
b1111111110000001000100001111110100111001001010001101101000111010100001110011101 0
b1011010011000100011110001100001111011110111011100110111010110110 -
b1011010011000100011110001100001111011110111011100110111010110110 #
b10100 +
b1000011111101001110010010100011011010001011101000011100111011101111111000000100 (
b1000011111101001110010010100011011010001011101000011100111011101111111000000100 *
b1111011100110000100111000110000010110110010101000111001001011000 )
b1111011100110000100111000110000010110110010101000111001001011000 ,
b10100 '
1!
#200000
0!
#205000
b1101100011001101101011001111010111001110110110011000100100111010 &
b1101100011001101101011001111010111001110110110011000100100111010 /
b1101100011001101101011001111010111001110110110011000100100111010 2
b1111101001001000111101100010000111101110010101111011110000011110 .
b1111101001001000111101100010000111101110010101111011110000011110 1
b11111000011100111010111111111000000100010000111111010011100110000000110110100011 %
b11111000011100111010111111111000000100010000111111010011100110000000110110100011 0
b1010011011001011101000101111111010011001000111010011000011101001 -
b1010011011001011101000101111111010011001000111010011000011101001 #
b10101 +
b1111111110000001000100001111110100111001001010001101101000111010100001110011101 (
b1111111110000001000100001111110100111001001010001101101000111010100001110011101 *
b1101100100001011001010101000000000000101100010010101110111110100 )
b1101100100001011001010101000000000000101100010010101110111110100 ,
b10101 '
1!
#210000
0!
#215000
b110111000010110110010111010011110000101111101110001010110100110 &
b110111000010110110010111010011110000101111101110001010110100110 /
b110111000010110110010111010011110000101111101110001010110100110 2
b110110010000001110010111100011101110010011110100000111111110110 .
b110110010000001110010111100011101110010011110100000111111110110 1
b11000001101101000111111100001110011101011111111100000010001010101111101001110011 %
b11000001101101000111111100001110011101011111111100000010001010101111101001110011 0
b10000010111110000000110000110111011111110101100101101010100010 -
b10000010111110000000110000110111011111110101100101101010100010 #
b10110 +
b11111000011100111010111111111000000100010000111111010011100110000000110110100011 (
b11111000011100111010111111111000000100010000111111010011100110000000110110100011 *
b1101100011001101101011001111010111001110110110011000100100111010 )
b1101100011001101101011001111010111001110110110011000100100111010 ,
b10110 '
1!
#220000
0!
#225000
b1010111101100100101100110110110111110011100100101010011000011110 &
b1010111101100100101100110110110111110011100100101010011000011110 /
b1010111101100100101100110110110111110011100100101010011000011110 2
b1111001011110110100010011111111000101100110000110101110100110100 .
b1111001011110110100010011111111000101100110000110101110100110100 1
b1111010011100111100000110110100011111110000111001110101101000110000001000101 %
b1111010011100111100000110110100011111110000111001110101101000110000001000101 0
b1010111110100010101101001010100111110000000010000001011110001100 -
b1010111110100010101101001010100111110000000010000001011110001100 #
b10111 +
b11000001101101000111111100001110011101011111111100000010001010101111101001110011 (
b11000001101101000111111100001110011101011111111100000010001010101111101001110011 *
b110111000010110110010111010011110000101111101110001010110100110 )
b110111000010110110010111010011110000101111101110001010110100110 ,
b10111 '
1!
#230000
0!
#235000
b1101010110111011111110001110001110110000000111111001000010110111 &
b1101010110111011111110001110001110110000000111111001000010110111 /
b1101010110111011111110001110001110110000000111111001000010110111 2
b1111110001101111010010000000100011010100110110111010001111111111 .
b1111110001101111010010000000100011010100110110111010001111111111 1
b111100000010001010000111101001110011110000011011010001111100000011100111010110 %
b111100000010001010000111101001110011110000011011010001111100000011100111010110 0
b1010000000101010110010110101101101111100011100110110100010101010 -
b1010000000101010110010110101101101111100011100110110100010101010 #
b11000 +
b1111010011100111100000110110100011111110000111001110101101000110000001000101 (
b1111010011100111100000110110100011111110000111001110101101000110000001000101 *
b1010111101100100101100110110110111110011100100101010011000011110 )
b1010111101100100101100110110110111110011100100101010011000011110 ,
b11000 '
1!
#240000
0!
#245000
b111011110011011010001111011010101010101010100001001000110101111 &
b111011110011011010001111011010101010101010100001001000110101111 /
b111011110011011010001111011010101010101010100001001000110101111 2
b1111010001011000011101100111111010010010111101001010110011101 .
b1111010001011000011101100111111010010010111101001010110011101 1
b11000111001110101100011110000001000101000011110100111001111011000101101000111110 %
b11000111001110101100011110000001000101000011110100111001111011000101101000111110 0
b1110100110110011010110010000101001111111000110010100000101000111 -
b1110100110110011010110010000101001111111000110010100000101000111 #
b11001 +
b111100000010001010000111101001110011110000011011010001111100000011100111010110 (
b111100000010001010000111101001110011110000011011010001111100000011100111010110 *
b1101010110111011111110001110001110110000000111111001000010110111 )
b1101010110111011111110001110001110110000000111111001000010110111 ,
b11001 '
1!
#250000
0!
#255000
b1110011110101011011101000101100000101010001111010011101111011111 &
b1110011110101011011101000101100000101010001111010011101111011111 /
b1110011110101011011101000101100000101010001111010011101111011111 2
b1000110011110101001111001011100110010101101001111111001110011011 .
b1000110011110101001111001011100110010101101001111111001110011011 1
b111011010001111101100011100111010110001111000000100010100010101010011100111101 %
b111011010001111101100011100111010110001111000000100010100010101010011100111101 0
b1011000010100001100000000011010001000001011011011010100001000011 -
b1011000010100001100000000011010001000001011011011010100001000011 #
b11010 +
b11000111001110101100011110000001000101000011110100111001111011000101101000111110 (
b11000111001110101100011110000001000101000011110100111001111011000101101000111110 *
b111011110011011010001111011010101010101010100001001000110101111 )
b111011110011011010001111011010101010101010100001001000110101111 ,
b11010 '
1!
#260000
0!
#265000
b101010000100110111001111110010001001010101001010100010011000 &
b101010000100110111001111110010001001010101001010100010011000 /
b101010000100110111001111110010001001010101001010100010011000 2
b111010000010100111101001000001011010110010001110101111000000000 .
b111010000010100111101001000001011010110010001110101111000000000 1
b100111001111010011101101000111110110001110011101011000100111000010001010001 %
b100111001111010011101101000111110110001110011101011000100111000010001010001 0
b1101110011101100101011001011111101110010110011010001100101010101 -
b1101110011101100101011001011111101110010110011010001100101010101 #
b11011 +
b111011010001111101100011100111010110001111000000100010100010101010011100111101 (
b111011010001111101100011100111010110001111000000100010100010101010011100111101 *
b1110011110101011011101000101100000101010001111010011101111011111 )
b1110011110101011011101000101100000101010001111010011101111011111 ,
b11011 '
1!
#270000
0!
#275000
b1011111110101101100010101100000000110010010101100101100110111110 &
b1011111110101101100010101100000000110010010101100101100110111110 /
b1011111110101101100010101100000000110010010101100101100110111110 2
b1100000110101011110110001110100111010110100100111001101100111000 .
b1100000110101011110110001110100111010110100100111001101100111000 1
b11010000100010100010000010011100111101001110110100011111011011011001110101100010 %
b11010000100010100010000010011100111101001110110100011111011011011001110101100010 0
b111001100011011110111001010001110010010010000100001110001011 -
b111001100011011110111001010001110010010010000100001110001011 #
b11100 +
b100111001111010011101101000111110110001110011101011000100111000010001010001 (
b100111001111010011101101000111110110001110011101011000100111000010001010001 *
b101010000100110111001111110010001001010101001010100010011000 )
b101010000100110111001111110010001001010101001010100010011000 ,
b11100 '
1!
#280000
0!
#285000
b1001110001111101001111011000001011101100010001110001110000001011 &
b1001110001111101001111011000001011101100010001110001110000001011 /
b1001110001111101001111011000001011101100010001110001110000001011 2
b1010001001101101111111110000010001001010100010001001101001111011 .
b1010001001101101111111110000010001001010100010001001101001111011 1
b10000011101011000101101000010001010001000001001110011110100100110010001111101101 %
b10000011101011000101101000010001010001000001001110011110100100110010001111101101 0
b110111100100111101010100101110011000110101110110100011011010011 -
b110111100100111101010100101110011000110101110110100011011010011 #
b11101 +
b11010000100010100010000010011100111101001110110100011111011011011001110101100010 (
b11010000100010100010000010011100111101001110110100011111011011011001110101100010 *
b1011111110101101100010101100000000110010010101100101100110111110 )
b1011111110101101100010101100000000110010010101100101100110111110 ,
b11101 '
1!
#290000
0!
#295000
b111110010010101101101000011001101011110011111011010111011001 &
b111110010010101101101000011001101011110011111011010111011001 /
b111110010010101101101000011001101011110011111011010111011001 2
b101001001110101101011011110101111110011000010010011011011100011 .
b101001001110101101011011110101111110011000010010011011011100011 1
b10100100011111011011000001110101100010110100001000101000100011010111001111010010 %
b10100100011111011011000001110101100010110100001000101000100011010111001111010010 0
b1111111010001011001111001001110101000010101001000001010011000 -
b1111111010001011001111001001110101000010101001000001010011000 #
b11110 +
b10000011101011000101101000010001010001000001001110011110100100110010001111101101 (
b10000011101011000101101000010001010001000001001110011110100100110010001111101101 *
b1001110001111101001111011000001011101100010001110001110000001011 )
b1001110001111101001111011000001011101100010001110001110000001011 ,
b11110 '
1!
#300000
0!
#305000
b1100110101001001100010000101110010010111001111001010000110110101 &
b1100110101001001100010000101110010010111001111001010000110110101 /
b1100110101001001100010000101110010010111001111001010000110110101 2
b1111100000010010110010100010101100011100001101111110011100001001 .
b1111100000010010110010100010101100011100001101111110011100001001 1
b11111110011110100101010010001111101101100000111010110001011001111100010100010001 %
b11111110011110100101010010001111101101100000111010110001011001111100010100010001 0
b1010101111101111000001101111001111100000100011011001110101010100 -
b1010101111101111000001101111001111100000100011011001110101010100 #
b11111 +
b10100100011111011011000001110101100010110100001000101000100011010111001111010010 (
b10100100011111011011000001110101100010110100001000101000100011010111001111010010 *
b111110010010101101101000011001101011110011111011010111011001 )
b111110010010101101101000011001101011110011111011010111011001 ,
b11111 '
1!
#310000
0!
#315000
b1111000100100100000011101101111111111011101100111111101101101010 &
b1111000100100100000011101101111111111011101100111111101101101010 /
b1111000100100100000011101101111111111011101100111111101101101010 2
b1011101110111011011101000111101101100101101101100101110001110110 .
b1011101110111011011101000111101101100101101101100101110001110110 1
b101000101000100011111111001111010010101001000111110110110000011101011000101100 %
b101000101000100011111111001111010010101001000111110110110000011101011000101100 0
b11001100110011110111001101001100100001001100100001000011010010 -
b11001100110011110111001101001100100001001100100001000011010010 #
b0 +
b11111110011110100101010010001111101101100000111010110001011001111100010100010001 (
b11111110011110100101010010001111101101100000111010110001011001111100010100010001 *
b1100110101001001100010000101110010010111001111001010000110110101 )
b1100110101001001100010000101110010010111001111001010000110110101 ,
b0 '
1!
#320000
0!
#325000
b1111111111111111111111111111111100000000000000000000000000000000 &
b1111111111111111111111111111111100000000000000000000000000000000 /
b1111111111111111111111111111111100000000000000000000000000000000 2
b1100110011001100110011001100110011001100110011001100110011001100 .
b1100110011001100110011001100110011001100110011001100110011001100 1
b101111111111111111111111111111111111111111111111111111111111110111111111111111 %
b101111111111111111111111111111111111111111111111111111111111110111111111111111 0
b0 -
b0 #
b1 +
b11111111111111111111111111111111111111111111111111111111111111111111111111111111 (
b11111111111111111111111111111111111111111111111111111111111111111111111111111111 *
b1111111111111111111111111111111111111111111111111111111111111111 )
b1111111111111111111111111111111111111111111111111111111111111111 ,
b1 '
1!
#330000
0!
