p_layer.v
module p_layer(input [63:0] state,      // origin data
               output wire [63:0] res); // p layer changed data

assign   res = {
state[0],state[4],state[8],state[12],state[16],state[20],state[24],state[28],
state[32],state[36],state[40],state[44],state[48],state[52],state[56],state[60],
state[1],state[5],state[9],state[13],state[17],state[21],state[25],state[29],
state[33],state[37],state[41],state[45],state[49],state[53],state[57],state[61],
state[2],state[6],state[10],state[14],state[18],state[22],state[26],state[30],
state[34],state[38],state[42],state[46],state[50],state[54],state[58],state[62],
state[3],state[7],state[11],state[15],state[19],state[23],state[27],state[31],
state[35],state[39],state[43],state[47],state[51],state[55],state[59],state[63]
};

endmodule

p_round.v
`include "p_layer.v"

module p_round(input [63:0] state,        // current cipher text
               input [79:0] keys,         // current key
               input [4:0] round_counter, // round counter
               output [63:0] res,         // next cipher text
               output [79:0] r_keys);     // next round key


wire   [63:0] tem0;
wire   [63:0] tem1;

reg [3:0] sbox[15:0]; // s box for sBoxLayer

initial begin
    sbox[0]  = 12;  sbox[1]  = 5; sbox[2]  = 6;  sbox[3]  = 11;
    sbox[4]  = 9;   sbox[5]  = 0; sbox[6]  = 10; sbox[7]  = 13;
    sbox[8]  = 3;  sbox[9]  = 14;sbox[10]  = 15; sbox[11]  = 8;
    sbox[12] = 4; sbox[13] = 7;sbox[14] = 1;  sbox[15] = 2;
end

// add round key
assign tem0 = state ^ keys[63:0];

// sBoxLayer
assign tem1 = {
sbox[tem0[3:0]],sbox[tem0[7:4]],sbox[tem0[11:8]],sbox[tem0[15:12]],
sbox[tem0[19:16]],sbox[tem0[23:20]],sbox[tem0[27:24]],sbox[tem0[31:28]],
sbox[tem0[35:32]],sbox[tem0[39:36]],sbox[tem0[43:40]],sbox[tem0[47:44]],
sbox[tem0[51:48]],sbox[tem0[55:52]],sbox[tem0[59:56]],sbox[tem0[63:60]]
};

// KeyExtend
assign     r_keys = {
sbox[keys[64:61]],keys[79:65],keys[40:0],(keys[45:41])^round_counter,keys[60:46]
};

// pLayer
p_layer      u_p_layer(
.state(tem1),
.res(res)
);

endmodule

p.v
`include "p_round.v"

module p(input [0:63] state,    // PlainText
         input [0:79] keys,     // key
         input clk,             // clock
         output [0:63] result);

reg   [0:7] cnt; /*synthesis syn_preserve = 1*/

reg   [0:63]  res;
reg   [0:79]  k;
wire  [0:63]  next_res;
wire  [0:79]  r_keys;

initial  begin
    cnt <= 0;
end

assign  result = res ^k[0:63];

// update the count,res,keys,ready
always @(posedge  clk)  begin
    cnt <= (cnt^31)? cnt+1: 0;
    res <= ((cnt) ?next_res:state) ;
    k   <= ((cnt) ?r_keys:keys) ;
end

p_round   u_p_round(
.res(next_res),
.r_keys(r_keys),
.state(res),
.keys(k),
.round_counter(cnt[3:7]));

// function [0:63]     end_conver ;
//     input     [0:63] data_in ;
//     parameter         MASK = 32'h3 ;
//     integer           k ;
//     begin
//         for(k = 0; k<64; k = k+1) begin
//             end_conver[63-k] = data_in[k] ;
//         end
//     end
// endfunction
endmodule

tb_p.v
`timescale  1ns / 1ps
`include "p.v"
module tb_p();
    parameter PERIOD = 10;
    reg clk;
    reg rst_n;
    reg [63:0] state;
    reg [79:0] keys;
    reg [23:0] counter;
    wire [63:0] result;
    
    // generate colck
    initial begin
        rst_n = 1'b1;
        clk   = 1'b0;
        forever #(PERIOD/2)
            clk = ~clk;
    end
    
    initial begin
        // state = 64'hffff_ffff_ffff_ffff;
        // keys  = 80'hffff_ffff_ffff_ffff_ffff;
        state    = 64'h0000_0000_0000_0000;
        keys     = 80'h0000_0000_0000_0000_0000;
    end
    
    
    p u_p(
    .result(result),
    .state(state),
    .keys(keys),
    .clk(clk));
    
    initial begin
        $dumpfile("./wave.vcd");
        $dumpvars(0, tb_p);
        #(PERIOD*40) $finish;
    end
    
endmodule

wave.vcd
$date
	Sat Feb 25 10:52:13 2023
$end
$version
	Icarus Verilog
$end
$timescale
	1ps
$end
$scope module tb_p $end
$var wire 64 ! result [63:0] $end
$var parameter 32 " PERIOD $end
$var reg 1 # clk $end
$var reg 80 $ keys [79:0] $end
$var reg 1 % rst_n $end
$var reg 64 & state [63:0] $end
$scope module u_p $end
$var wire 1 # clk $end
$var wire 80 ' keys [0:79] $end
$var wire 64 ( result [0:63] $end
$var wire 64 ) state [0:63] $end
$var wire 80 * r_keys [0:79] $end
$var wire 64 + next_res [0:63] $end
$var reg 8 , cnt [0:7] $end
$var reg 80 - k [0:79] $end
$var reg 64 . res [0:63] $end
$scope module u_p_round $end
$var wire 80 / keys [0:79] $end
$var wire 5 0 round_counter [0:4] $end
$var wire 64 1 state [0:63] $end
$var wire 64 2 tem0 [0:63] $end
$var wire 64 3 tem1 [0:63] $end
$var wire 64 4 res [0:63] $end
$var wire 80 5 r_keys [0:79] $end
$scope module u_pLayer $end
$var wire 64 6 state [0:63] $end
$var wire 64 7 res [0:63] $end
$upscope $end
$upscope $end
$upscope $end
$upscope $end
$enddefinitions $end
$comment Show the parameter values. $end
$dumpall
b1010 "
$end
#0
$dumpvars
bx 7
bx 6
bx 5
bx 4
bx 3
bx 2
bx 1
b0 0
bx /
bx .
bx -
b0 ,
bx +
bx *
b0 )
bx (
b0 '
b0 &
1%
b0 $
0#
bx !
$end
#5000
b1111111111111111111111111111111100000000000000000000000000000000 +
b1111111111111111111111111111111100000000000000000000000000000000 4
b1111111111111111111111111111111100000000000000000000000000000000 7
b1100110011001100110011001100110011001100110011001100110011001100 3
b1100110011001100110011001100110011001100110011001100110011001100 6
b0 !
b0 (
b0 2
b11000000000000000000000000000000000000000000000000000000000000001000000000000000 *
b11000000000000000000000000000000000000000000000000000000000000001000000000000000 5
b1 0
b0 -
b0 /
b0 .
b0 1
b1 ,
1#
#10000
0#
#15000
b1000000011111111000000001111111111111111000000001000000000000000 +
b1000000011111111000000001111111111111111000000001000000000000000 4
b1000000011111111000000001111111111111111000000001000000000000000 7
b1011001000100010001000100010001011001100110011001100110011001100 3
b1011001000100010001000100010001011001100110011001100110011001100 6
b1010000000000000001100000000000000000000000000000000000000000010000000000000000 *
b1010000000000000001100000000000000000000000000000000000000000010000000000000000 5
b11111111111111111111111111111100000000000000000000000000000000 2
b11111111111111111111111111111100000000000000000000000000000000 !
b11111111111111111111111111111100000000000000000000000000000000 (
b10 0
b11000000000000000000000000000000000000000000000000000000000000001000000000000000 -
b11000000000000000000000000000000000000000000000000000000000000001000000000000000 /
b1111111111111111111111111111111100000000000000000000000000000000 .
b1111111111111111111111111111111100000000000000000000000000000000 1
b10 ,
1#
#20000
0#
#25000
b100000000110110110010000011011110110111110010001000110000001001 +
b100000000110110110010000011011110110111110010001000110000001001 4
b100000000110110110010000011011110110111110010001000110000001001 7
b111110000100010010100110010001000100010110011000011110011000101 3
b111110000100010010100110010001000100010110011000011110011000101 6
b1100000000000000000101000000000000000110000000000000000000000011000000000000000 *
b1100000000000000000101000000000000000110000000000000000000000011000000000000000 5
b1101000011111111000110001111111111111111000000001000000000000001 2
b1101000011111111000110001111111111111111000000001000000000000001 !
b1101000011111111000110001111111111111111000000001000000000000001 (
b11 0
b1010000000000000001100000000000000000000000000000000000000000010000000000000000 -
b1010000000000000001100000000000000000000000000000000000000000010000000000000000 /
b1000000011111111000000001111111111111111000000001000000000000000 .
b1000000011111111000000001111111111111111000000001000000000000000 1
b11 ,
1#
#30000
0#
#35000
b111001111000010110011010010011010110110000110010010001101011001 +
b111001111000010110011010010011010110110000110010010001101011001 4
b111001111000010110011010010011010110110000110010010001101011001 7
b110110010111010010001101011110110001001010000110011010011000011 3
b110110010111010010001101011110110001001010000110011010011000011 6
b10110000000000000000110000000000000000010100000000000000011000100000000000000000 *
b10110000000000000000110000000000000000010100000000000000011000100000000000000000 5
b10000000110110110000100011011110110100110010001000110000001000 2
b10000000110110110000100011011110110100110010001000110000001000 !
b10000000110110110000100011011110110100110010001000110000001000 (
b100 0
b1100000000000000000101000000000000000110000000000000000000000011000000000000000 -
b1100000000000000000101000000000000000110000000000000000000000011000000000000000 /
b100000000110110110010000011011110110111110010001000110000001001 .
b100000000110110110010000011011110110111110010001000110000001001 1
b100 ,
1#
#40000
0#
#45000
b100000111010111101111100101100001010011000111100100010001000110 +
b100000111010111101111100101100001010011000111100100010001000110 4
b100000111010111101111100101100001010011000111100100010001000110 7
b100101101000110010001010110101010001101000011100110101110111000 3
b100101101000110010001010110101010001101000011100110101110111000 6
b10010000000000000001011000000000000000011000000000000000001010101000000000001100 *
b10010000000000000001011000000000000000011000000000000000001010101000000000001100 5
b1100001111000010110000010010011010110111010110010010001100111011 2
b1100001111000010110000010010011010110111010110010010001100111011 !
b1100001111000010110000010010011010110111010110010010001100111011 (
b101 0
b10110000000000000000110000000000000000010100000000000000011000100000000000000000 -
b10110000000000000000110000000000000000010100000000000000011000100000000000000000 /
b111001111000010110011010010011010110110000110010010001101011001 .
b111001111000010110011010010011010110110000110010010001101011001 1
b101 ,
1#
#50000
0#
#55000
b1100000101110111110000110000110101101011000101111110100011100 +
b1100000101110111110000110000110101101011000101111110100011100 4
b1100000101110111110000110000110101101011000101111110100011100 7
b111010101111101111100110000001100000110111000011001100110100100 3
b111010101111101111100110000001100000110111000011001100110100100 6
b11001001000000000000000101100000000000000001100110000000000000101 *
b11001001000000000000000101100000000000000001100110000000000000101 5
b1101000111010111101010000101100001010010100111100100010001101100 2
b1101000111010111101010000101100001010010100111100100010001101100 !
b1101000111010111101010000101100001010010100111100100010001101100 (
b110 0
b10010000000000000001011000000000000000011000000000000000001010101000000000001100 -
b10010000000000000001011000000000000000011000000000000000001010101000000000001100 /
b100000111010111101111100101100001010011000111100100010001000110 .
b100000111010111101111100101100001010011000111100100010001000110 1
b110 ,
1#
#60000
0#
#65000
b111010100000101001011011011001111110111111111100010110100100 +
b111010100000101001011011011001111110111111111100010110100100 4
b111010100000101001011011011001111110111111111100010110100100 7
b101001101100010101011111010010111110010111101100010011101100010 3
b101001101100010101011111010010111110010111101100010011101100010 6
b10100000000000001010000000000000001100100100000000000000010110111000000000000110 *
b10100000000000001010000000000000001100100100000000000000010110111000000000000110 5
b1100000101111011010100110000110101111101000101111110100101111 2
b1100000101111011010100110000110101111101000101111110100101111 !
b1100000101111011010100110000110101111101000101111110100101111 (
b111 0
b11001001000000000000000101100000000000000001100110000000000000101 -
b11001001000000000000000101100000000000000001100110000000000000101 /
b1100000101110111110000110000110101101011000101111110100011100 .
b1100000101110111110000110000110101101011000101111110100011100 1
b111 ,
1#
#70000
0#
#75000
b1011101110100000101110000100100010100001000100111110000010000000 +
b1011101110100000101110000100100010100001000100111110000010000000 4
b1011101110100000101110000100100010100001000100111110000010000000 7
b1111000111111100110000001000101010010100100000100100000000100010 3
b1111000111111100110000001000101010010100100000100100000000100010 6
b11010000000000001101010000000000000101000000000000000110010011000000000000001011 *
b11010000000000001101010000000000000101000000000000000110010011000000000000001011 5
b1010111010100000000001011011011001001100101111111100010111111111 2
b1010111010100000000001011011011001001100101111111100010111111111 !
b1010111010100000000001011011011001001100101111111100010111111111 (
b1000 0
b10100000000000001010000000000000001100100100000000000000010110111000000000000110 -
b10100000000000001010000000000000001100100100000000000000010110111000000000000110 /
b111010100000101001011011011001111110111111111100010110100100 .
b111010100000101001011011011001111110111111111100010110100100 1
b1000 ,
1#
#80000
0#
#85000
b1111101010010100001101000010001110101001000101000010001100111000 +
b1111101010010100001101000010001110101001000101000010001100111000 4
b1111101010010100001101000010001110101001000101000010001100111000 7
b1010100011111100101001001001001110000000010110110001101001000100 3
b1010100011111100101001001001001110000000010110110001101001000100 6
b110000000000010111101000000000000110101000000000000010100001001000000011001001 *
b110000000000010111101000000000000110101000000000000010100001001000000011001001 5
b110101110100000011011000100100010110101000100111110011011001100 2
b110101110100000011011000100100010110101000100111110011011001100 !
b110101110100000011011000100100010110101000100111110011011001100 (
b1001 0
b11010000000000001101010000000000000101000000000000000110010011000000000000001011 -
b11010000000000001101010000000000000101000000000000000110010011000000000000001011 /
b1011101110100000101110000100100010100001000100111110000010000000 .
b1011101110100000101110000100100010100001000100111110000010000000 1
b1001 ,
1#
#90000
0#
#95000
b110100111110010111000100010110101100011011010000100110101010100 +
b110100111110010111000100010110101100011011010000100110101010100 4
b110100111110010111000100010110101100011011010000100110101010100 7
b100111111100000100100010110101110001011111010010110010110000100 3
b100111111100000100100010110101110001011111010010110010110000100 6
b11100000000110010010011000000000001011110100000000000011010101010000000001010000 *
b11100000000110010010011000000000001011110100000000000011010101010000000001010000 5
b1100101010010101010011100010001110110011100101000010000110111100 2
b1100101010010101010011100010001110110011100101000010000110111100 !
b1100101010010101010011100010001110110011100101000010000110111100 (
b1010 0
b110000000000010111101000000000000110101000000000000010100001001000000011001001 -
b110000000000010111101000000000000110101000000000000010100001001000000011001001 /
b1111101010010100001101000010001110101001000101000010001100111000 .
b1111101010010100001101000010001110101001000101000010001100111000 1
b1010 ,
1#
#100000
0#
#105000
b101010010001010010010110110001111000011001100001010010110011101 +
b101010010001010010010110110001111000011001100001010010110011101 4
b101010010001010010010110110001111000011001100001010010110011101 7
b11111000011000010010010110011110010100011000111001000111000101 3
b11111000011000010010010110011110010100011000111001000111000101 6
b11110000000010100001110000000011001001001100000000000101111011011000000001101010 *
b11110000000010100001110000000011001001001100000000000101111011011000000001101010 5
b1000100111101011110001000010110101001100001010000100111000000001 2
b1000100111101011110001000010110101001100001010000100111000000001 !
b1000100111101011110001000010110101001100001010000100111000000001 (
b1011 0
b11100000000110010010011000000000001011110100000000000011010101010000000001010000 -
b11100000000110010010011000000000001011110100000000000011010101010000000001010000 /
b110100111110010111000100010110101100011011010000100110101010100 .
b110100111110010111000100010110101100011011010000100110101010100 1
b1011 ,
1#
#110000
0#
#115000
b1101011101011111100101010101111110100010001010001110010011001010 +
b1101011101011111100101010101111110100010001010001110010011001010 4
b1101011101011111100101010101111110100010001010001110010011001010 7
b1111100100111100000011011010110000011101001011001111110011011100 3
b1111100100111100000011011010110000011101001011001111110011011100 6
b10000000000011010101111000000001010000111000000001100100100111100000000010111101 *
b10000000000011010101111000000001010000111000000001100100100111100000000010111101 5
b1010010010000000010101110110000011100111111100001010000001110000 2
b1010010010000000010101110110000011100111111100001010000001110000 !
b1010010010000000010101110110000011100111111100001010000001110000 (
b1100 0
b11110000000010100001110000000011001001001100000000000101111011011000000001101010 -
b11110000000010100001110000000011001001001100000000000101111011011000000001101010 /
b101010010001010010010110110001111000011001100001010010110011101 .
b101010010001010010010110110001111000011001100001010010110011101 1
b1100 ,
1#
#120000
0#
#125000
b100010000100101010110000110010000010000001110000100000111111001 +
b100010000100101010110000110010000010000001110000100000111111001 4
b100010000100101010110000110010000010000001110000100000111111001 7
b110100000110010010000000000100010101111100110011110000001001 3
b110100000110010010000000000100010101111100110011110000001001 6
b1000000000101111011000000000001101010111100000000101000011101101000110010010011 *
b1000000000101111011000000000001101010111100000000101000011101101000110010010011 5
b101011101010010110010110101111011100001101010001000000001010100 2
b101011101010010110010110101111011100001101010001000000001010100 !
b101011101010010110010110101111011100001101010001000000001010100 (
b1101 0
b10000000000011010101111000000001010000111000000001100100100111100000000010111101 -
b10000000000011010101111000000001010000111000000001100100100111100000000010111101 /
b1101011101011111100101010101111110100010001010001110010011001010 .
b1101011101011111100101010101111110100010001010001110010011001010 1
b1101 ,
1#
#130000
0#
#135000
b1110001011001100100100000000010000110110001111110110110000010010 +
b1110001011001100100100000000010000110110001111110110110000010010 4
b1110001011001100100100000000010000110110001111110110110000010010 7
b1100100110110110000100111010000010001000001000111010111000110010 3
b1100100110110110000100111010000010001000001000111010111000110010 6
b1110001100100100110100000000010111101100000000000110101011111110000010100001110 *
b1110001100100100110100000000010111101100000000000110101011111110000010100001110 5
b10000110010111010000110010110111011111110000110100110001111 2
b10000110010111010000110010110111011111110000110100110001111 !
b10000110010111010000110010110111011111110000110100110001111 (
b1110 0
b1000000000101111011000000000001101010111100000000101000011101101000110010010011 -
b1000000000101111011000000000001101010111100000000101000011101101000110010010011 /
b100010000100101010110000110010000010000001110000100000111111001 .
b100010000100101010110000110010000010000001110000100000111111001 1
b1110 ,
1#
#140000
0#
#145000
b1100001101100110100000101100010111001101001101110101010000100001 +
b1100001101100110100000101100010111001101001101110101010000100001 4
b1100001101100110100000101100010111001101001101110101010000100001 7
b1110101100000001001000111100101001001100101100100000111010100111 3
b1110101100000001001000111100101001001100101100100000111010100111 6
b10000101000011100111000110010010011010000000001011110110001111000011010101111 *
b10000101000011100111000110010010011010000000001011110110001111000011010101111 5
b1001001101011110111110000000011011000000001111110101100101101101 2
b1001001101011110111110000000011011000000001111110101100101101101 !
b1001001101011110111110000000011011000000001111110101100101101101 (
b1111 0
b1110001100100100110100000000010111101100000000000110101011111110000010100001110 -
b1110001100100100110100000000010111101100000000000110101011111110000010100001110 /
b1110001011001100100100000000010000110110001111110110110000010010 .
b1110001011001100100100000000010000110110001111110110110000010010 1
b1111 ,
1#
#150000
0#
#155000
b101100101111101101101010101110011000010101001011101100110110110 +
b101100101111101101101010101110011000010101001011101100110110110 4
b101100101111101101101010101110011000010101001011101100110110110 7
b111101101001101100101000010110100111100101111011100111100011010 3
b111101101001101100101000010110100111100101111011100111100011010 6
b100000110101011110001000010100001110011100011001001001101010000000101111011000 *
b100000110101011110001000010100001110011100011001001001101010000000101111011000 5
b1101001111000111010011001111011110000000001101110000101011100110 2
b1101001111000111010011001111011110000000001101110000101011100110 !
b1101001111000111010011001111011110000000001101110000101011100110 (
b10000 0
b10000101000011100111000110010010011010000000001011110110001111000011010101111 -
b10000101000011100111000110010010011010000000001011110110001111000011010101111 /
b1100001101100110100000101100010111001101001101110101010000100001 .
b1100001101100110100000101100010111001101001101110101010000100001 1
b10000 ,
1#
#160000
0#
#165000
b1110011001111100111001000000111001110001101110001011011100010011 +
b1110011001111100111001000000111001110001101110001011011100010011 4
b1110011001111100111001000000111001110001101110001011011100010011 7
b1101111011110011000011011001001100101000101010111110110001010001 3
b1101111011110011000011011001001100101000101010111110110001010001 6
b11000001011110110000010000011010101111000100001010000111001100000100100100110101 *
b11000001011110110000010000011010101111000100001010000111001100000100100100110101 5
b111100110101000010101110100100011111011011000111001000000011110 2
b111100110101000010101110100100011111011011000111001000000011110 !
b111100110101000010101110100100011111011011000111001000000011110 (
b10001 0
b100000110101011110001000010100001110011100011001001001101010000000101111011000 -
b100000110101011110001000010100001110011100011001001001101010000000101111011000 /
b101100101111101101101010101110011000010101001011101100110110110 .
b101100101111101101101010101110011000010101001011101100110110110 1
b10001 ,
1#
#170000
0#
#175000
b111010100011101111101101101011010000000011110110101101101011001 +
b111010100011101111101101101011010000000011110110101101101011001 4
b111010100011101111101101101011010000000011110110101101101011001 7
b110110111001101000111000101100101000111001011111011110001101011 3
b110110111001101000111000101100101000111001011111011110001101011 6
b11001001001001101011100000101111011000001000001101010111100000010101000011100110 *
b11001001001001101011100000101111011000001000001101010111100000010101000011100110 5
b10011100000111111000000001010011001101111110100011000000100011 2
b10011100000111111000000001010011001101111110100011000000100011 !
b10011100000111111000000001010011001101111110100011000000100011 (
b10010 0
b11000001011110110000010000011010101111000100001010000111001100000100100100110101 -
b11000001011110110000010000011010101111000100001010000111001100000100100100110101 /
b1110011001111100111001000000111001110001101110001011011100010011 .
b1110011001111100111001000000111001110001101110001011011100010011 1
b10010 ,
1#
#180000
0#
#185000
b1011100101001000010000010100111000100011001100110010110010010011 +
b1011100101001000010000010100111000100011001100110010110010010011 4
b1011100101001000010000010100111000100011001100110010110010010011 7
b1000010010111000100100010010111000011100001000111100010001110011 3
b1000010010111000100100010010111000011100001000111100010001110011 6
b1101010000111001101100100100100110101110000010111101100000110011110101011110000 *
b1101010000111001101100100100100110101110000010111101100000110011110101011110000 5
b1011110000111011010011101111100111100000111110000000110011011000 2
b1011110000111011010011101111100111100000111110000000110011011000 !
b1011110000111011010011101111100111100000111110000000110011011000 (
b10011 0
b11001001001001101011100000101111011000001000001101010111100000010101000011100110 -
b11001001001001101011100000101111011000001000001101010111100000010101000011100110 /
b111010100011101111101101101011010000000011110110101101101011001 .
b111010100011101111101101101011010000000011110110101101101011001 1
b10011 ,
1#
#190000
0#
#195000
b101101101110101100010010000110111001111101100111101010101100011 +
b101101101110101100010010000110111001111101100111101010101100011 4
b101101101110101100010010000110111001111101100111101010101100011 7
b111101100001001111000111010111100101001101110100100110000111111 3
b111101100001001111000111010111100101001101110100100110000111111 6
b10111101010111100000110101000011100110110010010010011010111010101011110110000011 *
b10111101010111100000110101000011100110110010010010011010111010101011110110000011 5
b1101001101010100100110000110101011110100001101101100000010001010 2
b1101001101010100100110000110101011110100001101101100000010001010 !
b1101001101010100100110000110101011110100001101101100000010001010 (
b10100 0
b1101010000111001101100100100100110101110000010111101100000110011110101011110000 -
b1101010000111001101100100100100110101110000010111101100000110011110101011110000 /
b1011100101001000010000010100111000100011001100110010110010010011 .
b1011100101001000010000010100111000100011001100110010110010010011 1
b10100 ,
1#
#200000
0#
#205000
b101011001111001001000000011000101101000001001111000111101011010 +
b101011001111001001000000011000101101000001001111000111101011010 4
b101011001111001001000000011000101101000001001111000111101011010 7
b1101001101000001110011001000100001001111011011001001000111110 3
b1101001101000001110011001000100001001111011011001001000111110 6
b111101100000111011110101011110000011010100001110011011011100001001101011101 *
b111101100000111011110101011110000011010100001110011011011100001001101011101 5
b1110011000101011100001000100111001010100100101110100111110001001 2
b1110011000101011100001000100111001010100100101110100111110001001 !
b1110011000101011100001000100111001010100100101110100111110001001 (
b10101 0
b10111101010111100000110101000011100110110010010010011010111010101011110110000011 -
b10111101010111100000110101000011100110110010010010011010111010101011110110000011 /
b101101101110101100010010000110111001111101100111101010101100011 .
b101101101110101100010010000110111001111101100111101010101100011 1
b10101 ,
1#
#210000
0#
#215000
b1011111000011011101111100010000010011111110100100010110100011 +
b1011111000011011101111100010000010011111110100100010110100011 4
b1011111000011011101111100010000010011111110100100010110100011 7
b10101001110000011011110111111111110001100100010010010111001 3
b10101001110000011011110111111111110001100100010010010111001 6
b1000010011010111010000011110110000011101111010101111000001111100000111001101101 *
b1000010011010111010000011110110000011101111010101111000001111100000111001101101 5
b101000111001001010101111001101010101001100011111111110000110100 2
b101000111001001010101111001101010101001100011111111110000110100 !
b101000111001001010101111001101010101001100011111111110000110100 (
b10110 0
b111101100000111011110101011110000011010100001110011011011100001001101011101 -
b111101100000111011110101011110000011010100001110011011011100001001101011101 /
b101011001111001001000000011000101101000001001111000111101011010 .
b101011001111001001000000011000101101000001001111000111101011010 1
b10110 ,
1#
#220000
0#
#225000
b10011000101010001011011110011100111011010111110011111011001101 +
b10011000101010001011011110011100111011010111110011111011001101 4
b10011000101010001011011110011100111011010111110011111011001101 7
b11110011011111011011011001010111110000101011011111100111 3
b11110011011111011011011001010111110000101011011111100111 6
b1000001110011011010100001001101011101000001111011000001110101010010111100000111 *
b1000001110011011010100001001101011101000001111011000001110101010010111100000111 5
b101010110101000110101110011001000011101000011110011110110011101 2
b101010110101000110101110011001000011101000011110011110110011101 !
b101010110101000110101110011001000011101000011110011110110011101 (
b10111 0
b1000010011010111010000011110110000011101111010101111000001111100000111001101101 -
b1000010011010111010000011110110000011101111010101111000001111100000111001101101 /
b1011111000011011101111100010000010011111110100100010110100011 .
b1011111000011011101111100010000010011111110100100010110100011 1
b10111 ,
1#
#230000
0#
#235000
b1101001110100000010100110001001010001011010011010111101110110011 +
b1101001110100000010100110001001010001011010011010111101110110011 4
b1101001110100000010100110001001010001011010011010111101110110011 7
b1010110100011101001100001111111110010010100101010010001001010011 3
b1010110100011101001100001111111110010010100101010010001001010011 6
b11110101111000001110100000111001101101010000100110101110100011111101100000111010 *
b11110101111000001110100000111001101101010000100110101110100011111101100000111010 5
b110011111100111100001011010101001001111010000011111111100011000 2
b110011111100111100001011010101001001111010000011111111100011000 !
b110011111100111100001011010101001001111010000011111111100011000 (
b11000 0
b1000001110011011010100001001101011101000001111011000001110101010010111100000111 -
b1000001110011011010100001001101011101000001111011000001110101010010111100000111 /
b10011000101010001011011110011100111011010111110011111011001101 .
b10011000101010001011011110011100111011010111110011111011001101 1
b11000 ,
1#
#240000
0#
#245000
b111110110110010100100100000100111000010100010100010000011111010 +
b111110110110010100100100000100111000010100010100010000011111010 4
b111110110110010100100100000100111000010100010100010000011111010 7
b110101010011100100010000110100010110001100110010111000010110100 3
b110101010011100100010000110100010110001100110010111000010110100 6
b101011000001110101111010111100000111010000011100110110101011011011010111010001 *
b101011000001110101111010111100000111010000011100110110101011011011010111010001 5
b10011001000000101110110010101100111110010001001101010100111100 2
b10011001000000101110110010101100111110010001001101010100111100 !
b10011001000000101110110010101100111110010001001101010100111100 (
b11001 0
b11110101111000001110100000111001101101010000100110101110100011111101100000111010 -
b11110101111000001110100000111001101101010000100110101110100011111101100000111010 /
b1101001110100000010100110001001010001011010011010111101110110011 .
b1101001110100000010100110001001010001011010011010111101110110011 1
b11001 ,
1#
#250000
0#
#255000
b110001000000101000011001001100101000000111101000000000010111001 +
b110001000000101000011001001100101000000111101000000000010111001 4
b110001000000101000011001001100101000000111101000000000010111001 7
b101010000000010001001000000001110010001101110101101000001101 3
b101010000000010001001000000001110010001101110101101000001101 6
b10000110101110100010010101100000111010111101011110000011101011011110011011010101 *
b10000110101110100010010101100000111010111101011110000011101011011110011011010101 5
b101011010110101110011001011010111011111100011010001011001010111 2
b101011010110101110011001011010111011111100011010001011001010111 !
b101011010110101110011001011010111011111100011010001011001010111 (
b11010 0
b101011000001110101111010111100000111010000011100110110101011011011010111010001 -
b101011000001110101111010111100000111010000011100110110101011011011010111010001 /
b111110110110010100100100000100111000010100010100010000011111010 .
b111110110110010100100100000100111000010100010100010000011111010 1
b11010 ,
1#
#260000
0#
#265000
b110010111010101000011011010001000011111101111001100000010011111 +
b110010111010101000011011010001000011111101111001100000010011111 4
b110010111010101000011011010001000011111101111001100000010011111 7
b1100110000010011011100010111011111000011010110011101101011001 3
b1100110000010011011100010111011111000011010110011101101011001 6
b10001100110110101011000011010111010001001010110000011101011101110111000001110101 *
b10001100110110101011000011010111010001001010110000011101011101110111000001110101 5
b1110010010111111001010011111100110101011001000111000001100010100 2
b1110010010111111001010011111100110101011001000111000001100010100 !
b1110010010111111001010011111100110101011001000111000001100010100 (
b11011 0
b10000110101110100010010101100000111010111101011110000011101011011110011011010101 -
b10000110101110100010010101100000111010111101011110000011101011011110011011010101 /
b110001000000101000011001001100101000000111101000000000010111001 .
b110001000000101000011001001100101000000111101000000000010111001 1
b11011 ,
1#
#270000
0#
#275000
b110101001010000011001100011110001010100000011011000011000101111 +
b110101001010000011001100011110001010100000011011000011000101111 4
b110101001010000011001100011110001010100000011011000011000101111 7
b1111011000010100001111101000000001000010111000111011100010011 3
b1111011000010100001111101000000001000010111000111011100010011 6
b11110000011101011000110011011010101100001101011101000100110111000001110101110 *
b11110000011101011000110011011010101100001101011101000100110111000001110101110 5
b1110100100001111101111010111010101011011000100001101110111101000 2
b1110100100001111101111010111010101011011000100001101110111101000 !
b1110100100001111101111010111010101011011000100001101110111101000 (
b11100 0
b10001100110110101011000011010111010001001010110000011101011101110111000001110101 -
b10001100110110101011000011010111010001001010110000011101011101110111000001110101 /
b110010111010101000011011010001000011111101111001100000010011111 .
b110010111010101000011011010001000011111101111001100000010011111 1
b11100 ,
1#
#280000
0#
#285000
b1100011110011011100011111111000000001010010010001101111100110101 +
b1100011110011011100011111111000000001010010010001101111100110101 4
b1100011110011011100011111111000000001010010010001101111100110101 7
b1101100100000001011111011111110111000110010111011010000110001001 3
b1101100100000001011111011111110111000110010111011010000110001001 6
b11010000011101011100001111000001110101100011001101101010110011011101110100010011 *
b11010000011101011100001111000001110101100011001101101010110011011101110100010011 5
b111010001011110110101111010011100000010000101110110111010110100 2
b111010001011110110101111010011100000010000101110110111010110100 !
b111010001011110110101111010011100000010000101110110111010110100 (
b11101 0
b11110000011101011000110011011010101100001101011101000100110111000001110101110 -
b11110000011101011000110011011010101100001101011101000100110111000001110101110 /
b110101001010000011001100011110001010100000011011000011000101111 .
b110101001010000011001100011110001010100000011011000011000101111 1
b11101 ,
1#
#290000
0#
#295000
b100101000111000110001011110000000000010100000111111101110100001 +
b100101000111000110001011110000000000010100000111111101110100001 4
b100101000111000110001011110000000000010100000111111101110100001 7
b101110100010001100101001011010101110100110110001000000000100011 3
b101110100010001100101001011010101110100110110001000000000100011 6
b10001011101000100111101000001110101110000111100000111010110010010110110101011001 *
b10001011101000100111101000001110101110000111100000111010110010010110110101011001 5
b1011111101110010011000011000111011100011110111011010111111000 2
b1011111101110010011000011000111011100011110111011010111111000 !
b1011111101110010011000011000111011100011110111011010111111000 (
b11110 0
b11010000011101011100001111000001110101100011001101101010110011011101110100010011 -
b11010000011101011100001111000001110101100011001101101010110011011101110100010011 /
b1100011110011011100011111111000000001010010010001101111100110101 .
b1100011110011011100011111111000000001010010010001101111100110101 1
b11110 ,
1#
#300000
0#
#305000
b11100011010010111100000100110000110100011000110101001101000101 +
b11100011010010111100000100110000110100011000110101001101000101 4
b11100011010010111100000100110000110100011000110101001101000101 7
b100010111101111100000100001000110001111001010000100010110100011 3
b100010111101111100000100001000110001111001010000100010110100011 6
b1101101101010110011000101110100010011110100000111010111000000001000011101011001 *
b1101101101010110011000101110100010011110100000111010111000000001000011101011001 5
b1100000110011010101111111110111010111010111110111100000101101000 2
b1100000110011010101111111110111010111010111110111100000101101000 !
b1100000110011010101111111110111010111010111110111100000101101000 (
b11111 0
b10001011101000100111101000001110101110000111100000111010110010010110110101011001 -
b10001011101000100111101000001110101110000111100000111010110010010110110101011001 /
b100101000111000110001011110000000000010100000111111101110100001 .
b100101000111000110001011110000000000010100000111111101110100001 1
b11111 ,
1#
#310000
0#
