p_layer.v
module p_layer(input [63:0] state,      // origin data
               output wire [63:0] res); // p layer changed data

assign   res = {
state[0],state[4],state[8],state[12],state[16],state[20],state[24],state[28],
state[32],state[36],state[40],state[44],state[48],state[52],state[56],state[60],
state[1],state[5],state[9],state[13],state[17],state[21],state[25],state[29],
state[33],state[37],state[41],state[45],state[49],state[53],state[57],state[61],
state[2],state[6],state[10],state[14],state[18],state[22],state[26],state[30],
state[34],state[38],state[42],state[46],state[50],state[54],state[58],state[62],
state[3],state[7],state[11],state[15],state[19],state[23],state[27],state[31],
state[35],state[39],state[43],state[47],state[51],state[55],state[59],state[63]
};

endmodule

p_round.v
`include "p_layer.v"

module p_round(input [63:0] state,        // current cipher text
               input [79:0] keys,         // current key
               input [4:0] round_counter, // round counter
               output [63:0] res,         // next cipher text
               output [79:0] r_keys);     // next round key


wire   [63:0] tem0;
wire   [63:0] tem1;

reg [3:0] sbox[15:0]; // s box for sBoxLayer

initial begin
    sbox[0]  = 12;  sbox[1]  = 5; sbox[2]  = 6;  sbox[3]  = 11;
    sbox[4]  = 9;   sbox[5]  = 0; sbox[6]  = 10; sbox[7]  = 13;
    sbox[8]  = 3;  sbox[9]  = 14;sbox[10]  = 15; sbox[11]  = 8;
    sbox[12] = 4; sbox[13] = 7;sbox[14] = 1;  sbox[15] = 2;
end

// add round key
assign tem0 = state ^ keys[63:0];

// sBoxLayer
assign tem1 = {
sbox[tem0[3:0]],sbox[tem0[7:4]],sbox[tem0[11:8]],sbox[tem0[15:12]],
sbox[tem0[19:16]],sbox[tem0[23:20]],sbox[tem0[27:24]],sbox[tem0[31:28]],
sbox[tem0[35:32]],sbox[tem0[39:36]],sbox[tem0[43:40]],sbox[tem0[47:44]],
sbox[tem0[51:48]],sbox[tem0[55:52]],sbox[tem0[59:56]],sbox[tem0[63:60]]
};

// KeyExtend
assign     r_keys = {
sbox[keys[64:61]],keys[79:65],keys[40:0],(keys[45:41])^round_counter,keys[60:46]
};

// pLayer
p_layer      u_p_layer(
.state(tem1),
.res(res)
);

endmodule

p.v
`include "p_round.v"

module p(input clk,             // clock
         input [63:0] state,    // PlainText
         input [79:0] keys,     // key
         output [63:0] result);
    
    reg   [7:0] cnt; /*synthesis syn_preserve = 1*/
    
    reg   [63:0]  res;
    reg   [79:0]  k;
    wire  [63:0]  next_res;
    wire  [79:0]  r_keys;
    
    initial  begin
        cnt <= 0;
    end
    
    assign  result = res ^k[63:0];
    
    // update the count,res,keys,ready
    always @(posedge  clk)  begin
        cnt <= (cnt^31)? cnt+1: 0;
        res <= ((cnt) ?next_res:state) ;
        k   <= ((cnt) ?r_keys:keys) ;
    end
    
    p_round   u_p_round(
    .res(next_res),
    .r_keys(r_keys),
    .state(res),
    .keys(k),
    .round_counter(cnt[7:3]));
    
endmodule

tb_p.v
`timescale  1ns / 1ps
`include "p.v"
module tb_p();
    parameter PERIOD = 10;
    reg clk;
    reg rst_n;
    reg [63:0] state;
    reg [79:0] keys;
    reg [23:0] counter;
    wire [63:0] result;
    
    // generate colck
    initial begin
        rst_n = 1'b1;
        clk   = 1'b0;
        forever #(PERIOD/2)
            clk = ~clk;
    end
    
    initial begin
        state = 64'hffff_ffff_ffff_ffff;
        keys  = 80'hffff_ffff_ffff_ffff_ffff;
    end
    
    
    p u_p(
    .result(result),
    .state(state),
    .keys(keys),
    .clk(clk));
    
    initial begin
        $dumpfile("./wave.vcd");
        $dumpvars(0, u_p);
        #(PERIOD*40) $finish;
    end
    
endmodule

wave.vcd
$date
	Fri Feb 24 20:18:11 2023
$end
$version
	Icarus Verilog
$end
$timescale
	1ps
$end
$scope module tb_p $end
$scope module u_p $end
$var wire 1 ! clk $end
$var wire 80 " keys [79:0] $end
$var wire 64 # result [63:0] $end
$var wire 64 $ state [63:0] $end
$var wire 80 % r_keys [79:0] $end
$var wire 64 & next_res [63:0] $end
$var reg 8 ' cnt [7:0] $end
$var reg 80 ( k [79:0] $end
$var reg 64 ) res [63:0] $end
$scope module u_p_round $end
$var wire 80 * keys [79:0] $end
$var wire 5 + round_counter [4:0] $end
$var wire 64 , state [63:0] $end
$var wire 64 - tem0 [63:0] $end
$var wire 64 . tem1 [63:0] $end
$var wire 64 / res [63:0] $end
$var wire 80 0 r_keys [79:0] $end
$scope module u_p_layer $end
$var wire 64 1 state [63:0] $end
$var wire 64 2 res [63:0] $end
$upscope $end
$upscope $end
$upscope $end
$upscope $end
$enddefinitions $end
$comment Show the parameter values. $end
$dumpall
$end
#0
$dumpvars
bx 2
bx 1
bx 0
bx /
bx .
bx -
bx ,
b0 +
bx *
bx )
bx (
b0 '
bx &
bx %
b1111111111111111111111111111111111111111111111111111111111111111 $
bx #
b11111111111111111111111111111111111111111111111111111111111111111111111111111111 "
0!
$end
#5000
b11111111111111111111111111111111 &
b11111111111111111111111111111111 /
b11111111111111111111111111111111 2
b1100110011001100110011001100110011001100110011001100110011001100 .
b1100110011001100110011001100110011001100110011001100110011001100 1
b0 #
b0 -
b101111111111111111111111111111111111111111111111111111111111111111111111111111 %
b101111111111111111111111111111111111111111111111111111111111111111111111111111 0
b11111111111111111111111111111111111111111111111111111111111111111111111111111111 (
b11111111111111111111111111111111111111111111111111111111111111111111111111111111 *
b1111111111111111111111111111111111111111111111111111111111111111 )
b1111111111111111111111111111111111111111111111111111111111111111 ,
b1 '
1!
#10000
0!
#15000
b111111110000000000000000111111110000000011111111 &
b111111110000000000000000111111110000000011111111 /
b111111110000000000000000111111110000000011111111 2
b1100110011001100110011001100110000100010001000100010001000100010 .
b1100110011001100110011001100110000100010001000100010001000100010 1
b100010111111111111111111111111111111111111111111111111111111111111111111111111 %
b100010111111111111111111111111111111111111111111111111111111111111111111111111 0
b1111111111111111111111111111111100000000000000000000000000000000 -
b1111111111111111111111111111111100000000000000000000000000000000 #
b101111111111111111111111111111111111111111111111111111111111111111111111111111 (
b101111111111111111111111111111111111111111111111111111111111111111111111111111 *
b11111111111111111111111111111111 )
b11111111111111111111111111111111 ,
b10 '
1!
#20000
0!
#25000
b111100111100110000001100001100110000110000110011 &
b111100111100110000001100001100110000110000110011 /
b111100111100110000001100001100110000110000110011 2
b1100110000100010110011000010001000100010110011000010001000100010 .
b1100110000100010110011000010001000100010110011000010001000100010 1
b100010001011111111111111111111111111111111111111111111111111111111111111111111 %
b100010001011111111111111111111111111111111111111111111111111111111111111111111 0
b1111111111111111000000001111111111111111000000001111111100000000 -
b1111111111111111000000001111111111111111000000001111111100000000 #
b100010111111111111111111111111111111111111111111111111111111111111111111111111 (
b100010111111111111111111111111111111111111111111111111111111111111111111111111 *
b111111110000000000000000111111110000000011111111 )
b111111110000000000000000111111110000000011111111 ,
b11 '
1!
#30000
0!
#35000
b1101000100111100111100110000001100001100110000101101000100 &
b1101000100111100111100110000001100001100110000101101000100 /
b1101000100111100111100110000001100001100110000101101000100 2
b100010010110010010001001011001010111011010011000010001000100010 .
b100010010110010010001001011001010111011010011000010001000100010 1
b100010001000101111111111111111111111111111111111111111111111111111111111111111 %
b100010001000101111111111111111111111111111111111111111111111111111111111111111 0
b1111111111111111000011000011001111110011110011001111001111001100 -
b1111111111111111000011000011001111110011110011001111001111001100 #
b100010001011111111111111111111111111111111111111111111111111111111111111111111 (
b100010001011111111111111111111111111111111111111111111111111111111111111111111 *
b111100111100110000001100001100110000110000110011 )
b111100111100110000001100001100110000110000110011 ,
b100 '
1!
#40000
0!
#45000
b1101000100100000111100100001001100001100000011101101000111 &
b1101000100100000111100100001001100001100000011101101000111 /
b1101000100100000111100100001001100001100000011101101000111 2
b1000100010010010010001001011001010111011010011001000100001000010 .
b1000100010010010010001001011001010111011010011001000100001000010 1
b11010010001000100011111111111111111111111111111111111111111111111111111111111111 %
b11010010001000100011111111111111111111111111111111111111111111111111111111111111 0
b1111110010111011000011000011001111110011110011001111010010111011 -
b1111110010111011000011000011001111110011110011001111010010111011 #
b100010001000101111111111111111111111111111111111111111111111111111111111111111 (
b100010001000101111111111111111111111111111111111111111111111111111111111111111 *
b1101000100111100111100110000001100001100110000101101000100 )
b1101000100111100111100110000001100001100110000101101000100 ,
b101 '
1!
#50000
0!
#55000
b1000101101000101100000100101000101001101001010001011101111000110 &
b1000101101000101100000100101000101001101001010001011101111000110 /
b1000101101000101100000100101000101001101001010001011101111000110 2
b11100010010100001001001011100011011011010011011000100001001011 .
b11100010010100001001001011100011011011010011011000100001001011 1
b1011101001000100011111111111111111111111111111111111111111111111111111111111111 %
b1011101001000100011111111111111111111111111111111111111111111111111111111111111 0
b11110010111011011111000011011110110011110011111100010010111000 -
b11110010111011011111000011011110110011110011111100010010111000 #
b11010010001000100011111111111111111111111111111111111111111111111111111111111111 (
b11010010001000100011111111111111111111111111111111111111111111111111111111111111 *
b1101000100100000111100100001001100001100000011101101000111 )
b1101000100100000111100100001001100001100000011101101000111 ,
b110 '
1!
#60000
0!
#65000
b101111100111110000101100110001100011110011100011111101010011111 &
b101111100111110000101100110001100011110011100011111101010011111 /
b101111100111110000101100110001100011110011100011111101010011111 2
b1110101110011001110101110110100000011111011111011111100010011000 .
b1110101110011001110101110110100000011111011111011111100010011000 1
b1010101110100100011111111111111111111111111111111111111111111111111111111111111 %
b1010101110100100011111111111111111111111111111111111111111111111111111111111111 0
b1011010010111010011111011010111010110010110101110100010000111001 -
b1011010010111010011111011010111010110010110101110100010000111001 #
b1011101001000100011111111111111111111111111111111111111111111111111111111111111 (
b1011101001000100011111111111111111111111111111111111111111111111111111111111111 *
b1000101101000101100000100101000101001101001010001011101111000110 )
b1000101101000101100000100101000101001101001010001011101111000110 ,
b111 '
1!
#70000
0!
#75000
b1100011110000100001100010001001110111010010011100011000001011 &
b1100011110000100001100010001001110111010010011100011000001011 /
b1100011110000100001100010001001110111010010011100011000001011 2
b1100101000001100000100110101000101001110111000010101010011001010 .
b1100101000001100000100110101000101001110111000010101010011001010 1
b1010101010111010011111111111111111111111111111111111111111111110111111111111111 %
b1010101010111010011111111111111111111111111111111111111111111110111111111111111 0
b110000011000001111010011001110011100001100011100000010101100000 -
b110000011000001111010011001110011100001100011100000010101100000 #
b1 +
b1010101110100100011111111111111111111111111111111111111111111111111111111111111 (
b1010101110100100011111111111111111111111111111111111111111111111111111111111111 *
b101111100111110000101100110001100011110011100011111101010011111 )
b101111100111110000101100110001100011110011100011111101010011111 ,
b1000 '
1!
#80000
0!
#85000
b100101111000001100101111101011011101111000001000110110000111101 &
b100101111000001100101111101011011101111000001000110110000111101 /
b100101111000001100101111101011011101111000001000110110000111101 2
b1001001011101000101010000011001101110111111011010010110011010110 .
b1001001011101000101010000011001101110111111011010010110011010110 1
b11100101010101011101111111111111111111111111011111111111111111110111111111111111 %
b11100101010101011101111111111111111111111111011111111111111111110111111111111111 0
b10011100001111011110011101110110001000101101101011100111110100 -
b10011100001111011110011101110110001000101101101011100111110100 #
b1010101010111010011111111111111111111111111111111111111111111110111111111111111 (
b1010101010111010011111111111111111111111111111111111111111111110111111111111111 *
b1100011110000100001100010001001110111010010011100011000001011 )
b1100011110000100001100010001001110111010010011100011000001011 ,
b1001 '
1!
#90000
0!
#95000
b111010110001100101011100010010110000011110010111110100001010100 &
b111010110001100101011100010010110000011110010111110100001010100 /
b111010110001100101011100010010110000011110010111110100001010100 2
b110010010110101100000101100010101010110001110100001101110011110 .
b110010010110101100000101100010101010110001110100001101110011110 1
b11110010101010101111101111111111111111111011111111111111111110111111111111111 %
b11110010101010101111101111111111111111111011111111111111111110111111111111111 0
b1001010000111110011010000010000100010000111110110001001111000010 -
b1001010000111110011010000010000100010000111110110001001111000010 #
b11100101010101011101111111111111111111111111011111111111111111110111111111111111 (
b11100101010101011101111111111111111111111111011111111111111111110111111111111111 *
b100101111000001100101111101011011101111000001000110110000111101 )
b100101111000001100101111101011011101111000001000110110000111101 ,
b1010 '
1!
#100000
0!
#105000
b101011010110110111100110010101011000111110011100101000010111111 &
b101011010110110111100110010101011000111110011100101000010111111 /
b101011010110110111100110010101011000111110011100101000010111111 2
b1000111111011110100110110100110101100111010100001011001011110110 .
b1000111111011110100110110100110101100111010100001011001011110110 1
b11110001111001010101111101111111111111111111011111111111111111110111110111111111 %
b11110001111001010101111101111111111111111111011111111111111111110111110111111111 0
b10101011110011010100011101001001111100001101001001011110101011 -
b10101011110011010100011101001001111100001101001001011110101011 #
b11110010101010101111101111111111111111111011111111111111111110111111111111111 (
b11110010101010101111101111111111111111111011111111111111111110111111111111111 *
b111010110001100101011100010010110000011110010111110100001010100 )
b111010110001100101011100010010110000011110010111110100001010100 ,
b1011 '
1!
#110000
0!
#115000
b1111110110010100111110110011111111000111011101100010100011 &
b1111110110010100111110110011111111000111011101100010100011 /
b1111110110010100111110110011111111000111011101100010100011 2
b1100100101110110010110110011101101110111010011001110010011101100 .
b1100100101110110010110110011101101110111010011001110010011101100 1
b11111111000111100101111101111111111111111111011111011111111111110111110111111111 %
b11111111000111100101111101111111111111111111011111011111111111110111110111111111 0
b100111001001000011001101110100111000001100010010110101000000 -
b100111001001000011001101110100111000001100010010110101000000 #
b11110001111001010101111101111111111111111111011111111111111111110111110111111111 (
b11110001111001010101111101111111111111111111011111111111111111110111110111111111 *
b101011010110110111100110010101011000111110011100101000010111111 )
b101011010110110111100110010101011000111110011100101000010111111 ,
b1100 '
1!
#120000
0!
#125000
b10101000101000001110001001100001011110110110010001100101001000 &
b10101000101000001110001001100001011110110110010001100101001000 /
b10101000101000001110001001100001011110110110010001100101001000 2
b100000000001111011000011100011010000101010011111110001101000000 .
b100000000001111011000011100011010000101010011111110001101000000 1
b1101111111100011111111101111101111111111111011111011111111111110111110111111111 %
b1101111111100011111111101111101111111111111011111011111111111110111110111111111 0
b101110010001001101011000001101100100000111000101010010101011100 -
b101110010001001101011000001101100100000111000101010010101011100 #
b11111111000111100101111101111111111111111111011111011111111111110111110111111111 (
b11111111000111100101111101111111111111111111011111011111111111110111110111111111 *
b1111110110010100111110110011111111000111011101100010100011 )
b1111110110010100111110110011111111000111011101100010100011 ,
b1101 '
1!
#130000
0!
#135000
b1000010011000101100000111011100010001100011000010000011000011111 &
b1000010011000101100000111011100010001100011000010000011000011111 /
b1000010011000101100000111011100010001100011000010000011000011111 2
b1101100010011010101001100101001100101010110101000000000000000111 .
b1101100010011010101001100101001100101010110101000000000000000111 1
b100110111111110001111101111101111111111111011111011111111111110111110111110111 %
b100110111111110001111101111101111111111111011111011111111111110111110111110111 0
b1101010101010101110001110110111110000001001001100110010010110111 -
b1101010101010101110001110110111110000001001001100110010010110111 #
b1101111111100011111111101111101111111111111011111011111111111110111110111111111 (
b1101111111100011111111101111101111111111111011111011111111111110111110111111111 *
b10101000101000001110001001100001011110110110010001100101001000 )
b10101000101000001110001001100001011110110110010001100101001000 ,
b1110 '
1!
#140000
0!
#145000
b1101001011011100100010110000110001100001010001110101001101100 &
b1101001011011100100010110000110001100001010001110101001101100 /
b1101001011011100100010110000110001100001010001110101001101100 2
b11000110001101000111101011000000101001010011010011100010001110 .
b11000110001101000111101011000000101001010011010011100010001110 1
b110010011011111111111101111101111111111111011111011111011111110111110111110111 %
b110010011011111111111101111101111111111111011111011111011111110111110111110111 0
b1001101110111000011111000100111101010011100111100111101111101000 -
b1001101110111000011111000100111101010011100111100111101111101000 #
b100110111111110001111101111101111111111111011111011111111111110111110111110111 (
b100110111111110001111101111101111111111111011111011111111111110111110111110111 *
b1000010011000101100000111011100010001100011000010000011000011111 )
b1000010011000101100000111011100010001100011000010000011000011111 ,
b1111 '
1!
#150000
0!
#155000
b1000010001010100001110110100101000100010000111100001101101011111 &
b1000010001010100001110110100101000100010000111100001101101011111 /
b1000010001010100001110110100101000100010000111100001101101011111 2
b1000111011011110110100001011000010101110000110101010011000000001 .
b1000111011011110110100001011000010101110000110101010011000000001 1
b100011001001101111111101111101111101111111011111011111011111101111110111110111 %
b100011001001101111111101111101111101111111011111011111011111101111110111110111 0
b1110010100100110011011101001011001010011010101111001011110011011 -
b1110010100100110011011101001011001010011010101111001011110011011 #
b10 +
b110010011011111111111101111101111111111111011111011111011111110111110111110111 (
b110010011011111111111101111101111111111111011111011111011111110111110111110111 *
b1101001011011100100010110000110001100001010001110101001101100 )
b1101001011011100100010110000110001100001010001110101001101100 ,
b10000 '
1!
#160000
0!
#165000
b1000000101001011001100011110011110111101010100101101001000110110 &
b1000000101001011001100011110011110111101010100101101001000110110 /
b1000000101001011001100011110011110111101010100101101001000110110 2
b11111110100001110010100111001001111000010001001110011010001101 .
b11111110100001110010100111001001111000010001001110011010001101 1
b11010010001100100111111101111101111101111110111111011111011111001111110111110111 %
b11010010001100100111111101111101111101111110111111011111011111001111110111110111 0
b111101100101001110011001011110111111101011000001110011010101000 -
b111101100101001110011001011110111111101011000001110011010101000 #
b100011001001101111111101111101111101111111011111011111011111101111110111110111 (
b100011001001101111111101111101111101111111011111011111011111101111110111110111 *
b1000010001010100001110110100101000100010000111100001101101011111 )
b1000010001010100001110110100101000100010000111100001101101011111 ,
b10001 '
1!
#170000
0!
#175000
b110000100010001101101011110110000001010011010110011011010000000 &
b110000100010001101101011110110000001010011010110011011010000000 /
b110000100010001101101011110110000001010011010110011011010000000 2
b101010000100110000101100110101000111100101001001010101100010010 .
b101010000100110000101100110101000111100101001001010101100010010 1
b10111101001000110011111011111101111101111100111111011111011111001111110111110111 %
b10111101001000110011111011111101111101111100111111011111011111001111110111110111 0
b1111111000110110110001100000100001100010001011100010111111000001 -
b1111111000110110110001100000100001100010001011100010111111000001 #
b11010010001100100111111101111101111101111110111111011111011111001111110111110111 (
b11010010001100100111111101111101111101111110111111011111011111001111110111110111 *
b1000000101001011001100011110011110111101010100101101001000110110 )
b1000000101001011001100011110011110111101010100101101001000110110 ,
b10010 '
1!
#180000
0!
#185000
b10100110110011010001111000000000010110101110110000100100010111 &
b10100110110011010001111000000000010110101110110000100100010111 /
b10100110110011010001111000000000010110101110110000100100010111 2
b1101110110000100110101010000011110110110011010010100000100100000 .
b1101110110000100110101010000011110110110011010010100000100100000 1
b11101011110100100011110011111101111101111100111111011111011111001111101111110111 %
b11101011110100100011110011111101111101111100111111011111011111001111101111110111 0
b101111111101100010000100010001111010101000101111100101101110111 -
b101111111101100010000100010001111010101000101111100101101110111 #
b10111101001000110011111011111101111101111100111111011111011111001111110111110111 (
b10111101001000110011111011111101111101111100111111011111011111001111110111110111 *
b110000100010001101101011110110000001010011010110011011010000000 )
b110000100010001101101011110110000001010011010110011011010000000 ,
b10011 '
1!
#190000
0!
#195000
b1011001000010010000000010100110010000100111101010010111001010001 &
b1011001000010010000000010100110010000100111101010010111001010001 /
b1011001000010010000000010100110010000100111101010010111001010001 2
b1100000101100010110101001110010000101001110010000001100100000101 .
b1100000101100010110101001110010000101001110010000001100100000101 1
b1011110101111010011110011111101111101111100111110111111011111001111001111110111 %
b1011110101111010011110011111101111101111100111110111111011111001111001111110111 0
b1010101001110101100000100111111001001110001111111001011100000 -
b1010101001110101100000100111111001001110001111111001011100000 #
b11101011110100100011110011111101111101111100111111011111011111001111101111110111 (
b11101011110100100011110011111101111101111100111111011111011111001111101111110111 *
b10100110110011010001111000000000010110101110110000100100010111 )
b10100110110011010001111000000000010110101110110000100100010111 ,
b10100 '
1!
#200000
0!
#205000
b1110001110101110100111111011111100000000000111100000010111010011 &
b1110001110101110100111111011111100000000000111100000010111010011 /
b1110001110101110100111111011111100000000000111100000010111010011 2
b1010111101110111111000111000101110110011101000100010000100010011 .
b1010111101110111111000111000101110110011101000100010000100010011 1
b11100101111010111101110011111011111101111100111100111111011111001111001111110111 %
b11100101111010111101110011111011111101111100111100111111011111001111001111110111 0
b1000111011101111111101101000001100111011100010011101110110100110 -
b1000111011101111111101101000001100111011100010011101110110100110 #
b1011110101111010011110011111101111101111100111110111111011111001111001111110111 (
b1011110101111010011110011111101111101111100111110111111011111001111001111110111 *
b1011001000010010000000010100110010000100111101010010111001010001 )
b1011001000010010000000010100110010000100111101010010111001010001 ,
b10101 '
1!
#210000
0!
#215000
b1000011010000001110011001111111000000011000100101000101110100101 &
b1000011010000001110011001111111000000011000100101000101110100101 /
b1000011010000001110011001111111000000011000100101000101110100101 2
b1001011010100010011010100010101111001101001110100000000000101011 .
b1001011010100010011010100010101111001101001110100000000000101011 1
b11110010111101011110011110011111101111100111100111111011111001111001111101111 %
b11110010111101011110011110011111101111100111100111111011111001111001111101111 0
b11111101010101011010000111000000111111011000101111011000100100 -
b11111101010101011010000111000000111111011000101111011000100100 #
b11100101111010111101110011111011111101111100111100111111011111001111001111110111 (
b11100101111010111101110011111011111101111100111100111111011111001111001111110111 *
b1110001110101110100111111011111100000000000111100000010111010011 )
b1110001110101110100111111011111100000000000111100000010111010011 ,
b10110 '
1!
#220000
0!
#225000
b1110101110011111110110101010010101110001010010011110111010101011 &
b1110101110011111110110101010010101110001010010011110111010101011 /
b1110101110011111110110101010010101110001010010011110111010101011 2
b1111100100111101000110100100101101011011100010110110110111111011 .
b1111100100111101000110100100101101011011100010110110110111111011 1
b1111001011111110011110011111101111100111100111110111111001111001111001111 %
b1111001011111110011110011111101111100111100111110111111001111001111001111 0
b11101001110010001110110011000100111100011011100111100001001010 -
b11101001110010001110110011000100111100011011100111100001001010 #
b11110010111101011110011110011111101111100111100111111011111001111001111101111 (
b11110010111101011110011110011111101111100111100111111011111001111001111101111 *
b1000011010000001110011001111111000000011000100101000101110100101 )
b1000011010000001110011001111111000000011000100101000101110100101 ,
b10111 '
1!
#230000
0!
#235000
b1100010110001101001011110100011011011101000011000110001110100011 &
b1100010110001101001011110100011011011101000011000110001110100011 /
b1100010110001101001011110100011011011101000011000110001110100011 2
b1001101001110101000010000010100111111010011101100100101011010101 .
b1001101001110101000010000010100111111010011101100100101011010101 1
b100000000111100101110011110011111011111100111100111100111111000111001111001111 %
b100000000111100101110011110011111011111100111100111100111111000111001111001111 0
b1011101101100001011010110101001001111101101010001110101100100 -
b1011101101100001011010110101001001111101101010001110101100100 #
b11 +
b1111001011111110011110011111101111100111100111110111111001111001111001111 (
b1111001011111110011110011111101111100111100111110111111001111001111001111 *
b1110101110011111110110101010010101110001010010011110111010101011 )
b1110101110011111110110101010010101110001010010011110111010101011 ,
b11000 '
1!
#240000
0!
#245000
b11001011001000110000110010001011101101010111011110010100010110 &
b11001011001000110000110010001011101101010111011110010100010110 /
b11001011001000110000110010001011101101010111011110010100010110 2
b100101011000101110000100101000111100011110001000001110111101110 .
b100101011000101110000100101000111100011110001000001110111101110 1
b1100010000000011111110011110011110011111100011100111100111110100111001111001111 %
b1100010000000011111110011110011110011111100011100111100111110100111001111001111 0
b1001100101111110110000001000100111100001111100000001000001101100 -
b1001100101111110110000001000100111100001111100000001000001101100 #
b100000000111100101110011110011111011111100111100111100111111000111001111001111 (
b100000000111100101110011110011111011111100111100111100111111000111001111001111 *
b1100010110001101001011110100011011011101000011000110001110100011 )
b1100010110001101001011110100011011011101000011000110001110100011 ,
b11001 '
1!
#250000
0!
#255000
b110001011110010001000001010111110001100111110110011100000111101 &
b110001011110010001000001010111110001100111110110011100000111101 /
b110001011110010001000001010111110001100111110110011100000111101 2
b1110011110101110110111110101011100000001010011001000101100010100 .
b1110011110101110110111110101011100000001010011001000101100010100 1
b100110001000000001110001110011110011111010011100111100111100100111001111001111 %
b100110001000000001110001110011110011111010011100111100111100100111001111001111 0
b1100111000111011000011001110010111010001101001111001011011011001 -
b1100111000111011000011001110010111010001101001111001011011011001 #
b1100010000000011111110011110011110011111100011100111100111110100111001111001111 (
b1100010000000011111110011110011110011111100011100111100111110100111001111001111 *
b11001011001000110000110010001011101101010111011110010100010110 )
b11001011001000110000110010001011101101010111011110010100010110 ,
b11010 '
1!
#260000
0!
#265000
b1111100100001000001001010001001110010010011100011000001011111100 &
b1111100100001000001001010001001110010010011100011000001011111100 /
b1111100100001000001001010001001110010010011100011000001011111100 2
b110001010001001111011001100100000111100001000010101001100011101 .
b110001010001001111011001100100000111100001000010101001100011101 1
b11000010011000100001101001110011110011110010011100111100111100100111000111001111 %
b11000010011000100001101001110011110011110010011100111100111100100111000111001111 0
b111111010000001111011110000100010110000000010010100101111110010 -
b111111010000001111011110000100010110000000010010100101111110010 #
b100110001000000001110001110011110011111010011100111100111100100111001111001111 (
b100110001000000001110001110011110011111010011100111100111100100111001111001111 *
b110001011110010001000001010111110001100111110110011100000111101 )
b110001011110010001000001010111110001100111110110011100000111101 ,
b11011 '
1!
#270000
0!
#275000
b1110111111110111010001101011111100100100100000000111011110010111 &
b1110111111110111010001101011111100100100100000000111011110010111 /
b1110111111110111010001101011111100100100100000000111011110010111 2
b1011101110110010101100110001111110011011111100011000110110110001 .
b1011101110110010101100110001111110011011111100011000110110110001 1
b11001100001001100011001001110011110011110010011100011100111100100110100111001111 %
b11001100001001100011001001110011110011110010011100011100111100100110100111001111 0
b1110001101111011111010100011010010101110100000111111001100110011 -
b1110001101111011111010100011010010101110100000111111001100110011 #
b11000010011000100001101001110011110011110010011100111100111100100111000111001111 (
b11000010011000100001101001110011110011110010011100111100111100100111000111001111 *
b1111100100001000001001010001001110010010011100011000001011111100 )
b1111100100001000001001010001001110010010011100011000001011111100 ,
b11100 '
1!
#280000
0!
#285000
b1111100111101101111011111101000111000110001110000001011010100000 &
b1111100111101101111011111101000111000110001110000001011010100000 /
b1111100111101101111011111101000111000110001110000001011010100000 2
b11000000010101011011010011101100111110111000111001001101110111 .
b11000000010101011011010011101100111110111000111001001101110111 1
b1011100110000100111001001110001110011110010011010011100111100100100100111001111 %
b1011100110000100111001001110001110011110010011010011100111100100100100111001111 0
b1101110110000100100010011001100000111000011100100001111001011000 -
b1101110110000100100010011001100000111000011100100001111001011000 #
b11001100001001100011001001110011110011110010011100011100111100100110100111001111 (
b11001100001001100011001001110011110011110010011100011100111100100110100111001111 *
b1110111111110111010001101011111100100100100000000111011110010111 )
b1110111111110111010001101011111100100100100000000111011110010111 ,
b11101 '
1!
#290000
0!
#295000
b1000000101010000101010100101011100111101011100000110010101010010 &
b1000000101010000101010100101011100111101011100000110010101010010 /
b1000000101010000101010100101011100111101011100000110010101010010 2
b10101000100000111101001111000011010010110001100100111010000011 .
b10101000100000111101001111000011010010110001100100111010000011 1
b10110101110011000011001001101001110011110010010010011100111100100100100111000111 %
b10110101110011000011001001101001110011110010010010011100111100100100100111000111 0
b1000101110011100001000001111011101011010110010100101111101101111 -
b1000101110011100001000001111011101011010110010100101111101101111 #
b1011100110000100111001001110001110011110010011010011100111100100100100111001111 (
b1011100110000100111001001110001110011110010011010011100111100100100100111001111 *
b1111100111101101111011111101000111000110001110000001011010100000 )
b1111100111101101111011111101000111000110001110000001011010100000 ,
b11110 '
1!
#300000
0!
#305000
b110001111100000011110011011101000010010110111101111101110000010 &
b110001111100000011110011011101000010010110111101111101110000010 /
b110001111100000011110011011101000010010110111101111101110000010 2
b111001000110011000110101111110111101000010101110101110111000 .
b111001000110011000110101111110111101000010101110101110111000 1
b1011011010111001101001001001001110011110010010010011100011100100100100110100111 %
b1011011010111001101001001001001110011110010010010011100011100100100100110100111 0
b1011001100111001011001010111001110100001100000100010110010010101 -
b1011001100111001011001010111001110100001100000100010110010010101 #
b10110101110011000011001001101001110011110010010010011100111100100100100111000111 (
b10110101110011000011001001101001110011110010010010011100111100100100100111000111 *
b1000000101010000101010100101011100111101011100000110010101010010 )
b1000000101010000101010100101011100111101011100000110010101010010 ,
b11111 '
1!
#310000
0!
#315000
b110000111100000001101101010011001110010001101101011111000101000 &
b110000111100000001101101010011001110010001101101011111000101000 /
b110000111100000001101101010011001110010001101101011111000101000 2
b11001101000010011110001001100011110101010001110111101011000 .
b11001101000010011110001001100011110101010001110111101011000 1
b10100101101101011101001001001001110001110010010010011010011100111100100100100111 %
b10100101101101011101001001001001110001110010010010011010011100111100100100100111 0
b1011000110101001101101101001111010001110101011001011001000100101 -
b1011000110101001101101101001111010001110101011001011001000100101 #
b0 +
b1011011010111001101001001001001110011110010010010011100011100100100100110100111 (
b1011011010111001101001001001001110011110010010010011100011100100100100110100111 *
b110001111100000011110011011101000010010110111101111101110000010 )
b110001111100000011110011011101000010010110111101111101110000010 ,
b0 '
1!
#320000
0!
#325000
b11111111111111111111111111111111 &
b11111111111111111111111111111111 /
b11111111111111111111111111111111 2
b1100110011001100110011001100110011001100110011001100110011001100 .
b1100110011001100110011001100110011001100110011001100110011001100 1
b101111111111111111111111111111111111111111111111111111111111111111111111111111 %
b101111111111111111111111111111111111111111111111111111111111111111111111111111 0
b0 -
b0 #
b11111111111111111111111111111111111111111111111111111111111111111111111111111111 (
b11111111111111111111111111111111111111111111111111111111111111111111111111111111 *
b1111111111111111111111111111111111111111111111111111111111111111 )
b1111111111111111111111111111111111111111111111111111111111111111 ,
b1 '
1!
#330000
0!
#335000
b111111110000000000000000111111110000000011111111 &
b111111110000000000000000111111110000000011111111 /
b111111110000000000000000111111110000000011111111 2
b1100110011001100110011001100110000100010001000100010001000100010 .
b1100110011001100110011001100110000100010001000100010001000100010 1
b100010111111111111111111111111111111111111111111111111111111111111111111111111 %
b100010111111111111111111111111111111111111111111111111111111111111111111111111 0
b1111111111111111111111111111111100000000000000000000000000000000 -
b1111111111111111111111111111111100000000000000000000000000000000 #
b101111111111111111111111111111111111111111111111111111111111111111111111111111 (
b101111111111111111111111111111111111111111111111111111111111111111111111111111 *
b11111111111111111111111111111111 )
b11111111111111111111111111111111 ,
b10 '
1!
#340000
0!
